{"@t":"2026-06-27T16:21:32.1774581Z","@mt":"User profile is available. Using '{FullName}' as key repository and Windows DPAPI to encrypt keys at rest.","FullName":"C:\\Users\\Joseph\\AppData\\Local\\ASP.NET\\DataProtection-Keys","EventId":{"Id":63,"Name":"UsingProfileAsKeyRepositoryWithDPAPI"},"SourceContext":"Microsoft.AspNetCore.DataProtection.KeyManagement.XmlKeyManager"}
{"@t":"2026-06-27T16:21:32.3753536Z","@mt":"Hosting failed to start","@l":"Error","@x":"System.IO.IOException: Failed to bind to address http://127.0.0.1:5199: address already in use.\r\n ---> Microsoft.AspNetCore.Connections.AddressInUseException: Only one usage of each socket address (protocol/network address/port) is normally permitted.\r\n ---> System.Net.Sockets.SocketException (10048): Only one usage of each socket address (protocol/network address/port) is normally permitted.\r\n   at System.Net.Sockets.Socket.UpdateStatusAfterSocketErrorAndThrowException(SocketError error, Boolean disconnectOnFailure, String callerName)\r\n   at System.Net.Sockets.Socket.DoBind(EndPoint endPointSnapshot, SocketAddress socketAddress)\r\n   at System.Net.Sockets.Socket.Bind(EndPoint localEP)\r\n   at Microsoft.AspNetCore.Server.Kestrel.Transport.Sockets.SocketTransportOptions.CreateDefaultBoundListenSocket(EndPoint endpoint)\r\n   at Microsoft.AspNetCore.Server.Kestrel.Transport.Sockets.SocketConnectionListener.Bind()\r\n   --- End of inner exception stack trace ---\r\n   at Microsoft.AspNetCore.Server.Kestrel.Transport.Sockets.SocketConnectionListener.Bind()\r\n   at Microsoft.AspNetCore.Server.Kestrel.Transport.Sockets.SocketTransportFactory.BindAsync(EndPoint endpoint, CancellationToken cancellationToken)\r\n   at Microsoft.AspNetCore.Server.Kestrel.Core.Internal.Infrastructure.TransportManager.BindAsync(EndPoint endPoint, ConnectionDelegate connectionDelegate, EndpointConfig endpointConfig, CancellationToken cancellationToken)\r\n   at Microsoft.AspNetCore.Server.Kestrel.Core.KestrelServerImpl.<>c__DisplayClass28_0`1.<<StartAsync>g__OnBind|0>d.MoveNext()\r\n--- End of stack trace from previous location ---\r\n   at Microsoft.AspNetCore.Server.Kestrel.Core.Internal.AddressBinder.BindEndpointAsync(ListenOptions endpoint, AddressBindContext context, CancellationToken cancellationToken)\r\n   --- End of inner exception stack trace ---\r\n   at Microsoft.AspNetCore.Server.Kestrel.Core.Internal.AddressBinder.BindEndpointAsync(ListenOptions endpoint, AddressBindContext context, CancellationToken cancellationToken)\r\n   at Microsoft.AspNetCore.Server.Kestrel.Core.LocalhostListenOptions.BindAsync(AddressBindContext context, CancellationToken cancellationToken)\r\n   at Microsoft.AspNetCore.Server.Kestrel.Core.Internal.AddressBinder.AddressesStrategy.BindAsync(AddressBindContext context, CancellationToken cancellationToken)\r\n   at Microsoft.AspNetCore.Server.Kestrel.Core.KestrelServerImpl.BindAsync(CancellationToken cancellationToken)\r\n   at Microsoft.AspNetCore.Server.Kestrel.Core.KestrelServerImpl.StartAsync[TContext](IHttpApplication`1 application, CancellationToken cancellationToken)\r\n   at Microsoft.AspNetCore.Hosting.GenericWebHostService.StartAsync(CancellationToken cancellationToken)\r\n   at Microsoft.Extensions.Hosting.Internal.Host.<StartAsync>b__14_1(IHostedService service, CancellationToken token)\r\n   at Microsoft.Extensions.Hosting.Internal.Host.ForeachService[T](IEnumerable`1 services, CancellationToken token, Boolean concurrent, Boolean abortOnFirstException, List`1 exceptions, Func`3 operation)","EventId":{"Id":11,"Name":"HostedServiceStartupFaulted"},"SourceContext":"Microsoft.Extensions.Hosting.Internal.Host"}
{"@t":"2026-06-27T16:22:03.6310470Z","@mt":"User profile is available. Using '{FullName}' as key repository and Windows DPAPI to encrypt keys at rest.","FullName":"C:\\Users\\Joseph\\AppData\\Local\\ASP.NET\\DataProtection-Keys","EventId":{"Id":63,"Name":"UsingProfileAsKeyRepositoryWithDPAPI"},"SourceContext":"Microsoft.AspNetCore.DataProtection.KeyManagement.XmlKeyManager"}
{"@t":"2026-06-27T16:22:03.8550323Z","@mt":"Now listening on: {address}","address":"http://localhost:5199","EventId":{"Id":14,"Name":"ListeningOnAddress"},"SourceContext":"Microsoft.Hosting.Lifetime"}
{"@t":"2026-06-27T16:22:03.8594351Z","@mt":"Application started. Press Ctrl+C to shut down.","SourceContext":"Microsoft.Hosting.Lifetime"}
{"@t":"2026-06-27T16:22:03.8598780Z","@mt":"Hosting environment: {EnvName}","EnvName":"Development","SourceContext":"Microsoft.Hosting.Lifetime"}
{"@t":"2026-06-27T16:22:03.8599610Z","@mt":"Content root path: {ContentRoot}","ContentRoot":"C:\\Users\\Joseph\\Documents\\QueueIQ\\src\\QueueIQ.Web","SourceContext":"Microsoft.Hosting.Lifetime"}
{"@t":"2026-06-27T16:22:34.9348962Z","@mt":"Request starting {Protocol} {Method} {Scheme}://{Host}{PathBase}{Path}{QueryString} - {ContentType} {ContentLength}","@tr":"24c6920069aa40710ceb327baa859f2a","@sp":"6ee49c7b99a29ba0","Protocol":"HTTP/1.1","Method":"GET","ContentType":null,"ContentLength":null,"Scheme":"http","Host":"localhost:5199","PathBase":"","Path":"/join/joes-barbershop","QueryString":"","EventId":{"Id":1},"SourceContext":"Microsoft.AspNetCore.Hosting.Diagnostics","RequestId":"0HNMKD15V5L5S:00000001","RequestPath":"/join/joes-barbershop","ConnectionId":"0HNMKD15V5L5S"}
{"@t":"2026-06-27T16:22:34.9618516Z","@mt":"Failed to determine the https port for redirect.","@l":"Warning","@tr":"24c6920069aa40710ceb327baa859f2a","@sp":"6ee49c7b99a29ba0","EventId":{"Id":3,"Name":"FailedToDeterminePort"},"SourceContext":"Microsoft.AspNetCore.HttpsPolicy.HttpsRedirectionMiddleware","RequestId":"0HNMKD15V5L5S:00000001","RequestPath":"/join/joes-barbershop","ConnectionId":"0HNMKD15V5L5S"}
{"@t":"2026-06-27T16:22:34.9636567Z","@mt":"Executing endpoint '{EndpointName}'","@tr":"24c6920069aa40710ceb327baa859f2a","@sp":"6ee49c7b99a29ba0","EndpointName":"/join/{Slug} (/join/{Slug})","EventId":{"Name":"ExecutingEndpoint"},"SourceContext":"Microsoft.AspNetCore.Routing.EndpointMiddleware","RequestId":"0HNMKD15V5L5S:00000001","RequestPath":"/join/joes-barbershop","ConnectionId":"0HNMKD15V5L5S"}
{"@t":"2026-06-27T16:22:35.0245968Z","@mt":"Start processing HTTP request {HttpMethod} {Uri}","@tr":"24c6920069aa40710ceb327baa859f2a","@sp":"6ee49c7b99a29ba0","HttpMethod":"GET","Uri":"http://localhost:5088/api/businesses/joes-barbershop","EventId":{"Id":100,"Name":"RequestPipelineStart"},"SourceContext":"System.Net.Http.HttpClient.ApiClient.LogicalHandler","RequestId":"0HNMKD15V5L5S:00000001","RequestPath":"/join/joes-barbershop","ConnectionId":"0HNMKD15V5L5S","Scope":["HTTP GET http://localhost:5088/api/businesses/joes-barbershop"]}
{"@t":"2026-06-27T16:22:35.0273676Z","@mt":"Sending HTTP request {HttpMethod} {Uri}","@tr":"24c6920069aa40710ceb327baa859f2a","@sp":"6ee49c7b99a29ba0","HttpMethod":"GET","Uri":"http://localhost:5088/api/businesses/joes-barbershop","EventId":{"Id":100,"Name":"RequestStart"},"SourceContext":"System.Net.Http.HttpClient.ApiClient.ClientHandler","RequestId":"0HNMKD15V5L5S:00000001","RequestPath":"/join/joes-barbershop","ConnectionId":"0HNMKD15V5L5S","Scope":["HTTP GET http://localhost:5088/api/businesses/joes-barbershop"]}
{"@t":"2026-06-27T16:22:35.5014349Z","@mt":"Received HTTP response headers after {ElapsedMilliseconds}ms - {StatusCode}","@tr":"24c6920069aa40710ceb327baa859f2a","@sp":"6ee49c7b99a29ba0","ElapsedMilliseconds":472.3991,"StatusCode":200,"EventId":{"Id":101,"Name":"RequestEnd"},"SourceContext":"System.Net.Http.HttpClient.ApiClient.ClientHandler","HttpMethod":"GET","Uri":"http://localhost:5088/api/businesses/joes-barbershop","RequestId":"0HNMKD15V5L5S:00000001","RequestPath":"/join/joes-barbershop","ConnectionId":"0HNMKD15V5L5S","Scope":["HTTP GET http://localhost:5088/api/businesses/joes-barbershop"]}
{"@t":"2026-06-27T16:22:35.5094300Z","@mt":"End processing HTTP request after {ElapsedMilliseconds}ms - {StatusCode}","@tr":"24c6920069aa40710ceb327baa859f2a","@sp":"6ee49c7b99a29ba0","ElapsedMilliseconds":487.022,"StatusCode":200,"EventId":{"Id":101,"Name":"RequestPipelineEnd"},"SourceContext":"System.Net.Http.HttpClient.ApiClient.LogicalHandler","HttpMethod":"GET","Uri":"http://localhost:5088/api/businesses/joes-barbershop","RequestId":"0HNMKD15V5L5S:00000001","RequestPath":"/join/joes-barbershop","ConnectionId":"0HNMKD15V5L5S","Scope":["HTTP GET http://localhost:5088/api/businesses/joes-barbershop"]}
{"@t":"2026-06-27T16:22:35.5969174Z","@mt":"Executed endpoint '{EndpointName}'","@tr":"24c6920069aa40710ceb327baa859f2a","@sp":"6ee49c7b99a29ba0","EndpointName":"/join/{Slug} (/join/{Slug})","EventId":{"Id":1,"Name":"ExecutedEndpoint"},"SourceContext":"Microsoft.AspNetCore.Routing.EndpointMiddleware","RequestId":"0HNMKD15V5L5S:00000001","RequestPath":"/join/joes-barbershop","ConnectionId":"0HNMKD15V5L5S"}
{"@t":"2026-06-27T16:22:35.6003715Z","@mt":"Request finished {Protocol} {Method} {Scheme}://{Host}{PathBase}{Path}{QueryString} - {StatusCode} {ContentLength} {ContentType} {ElapsedMilliseconds}ms","@tr":"24c6920069aa40710ceb327baa859f2a","@sp":"6ee49c7b99a29ba0","ElapsedMilliseconds":667.1561,"StatusCode":200,"ContentType":"text/html; charset=utf-8","ContentLength":null,"Protocol":"HTTP/1.1","Method":"GET","Scheme":"http","Host":"localhost:5199","PathBase":"","Path":"/join/joes-barbershop","QueryString":"","EventId":{"Id":2},"SourceContext":"Microsoft.AspNetCore.Hosting.Diagnostics","RequestId":"0HNMKD15V5L5S:00000001","RequestPath":"/join/joes-barbershop","ConnectionId":"0HNMKD15V5L5S"}
{"@t":"2026-06-27T16:22:35.6088735Z","@mt":"Request starting {Protocol} {Method} {Scheme}://{Host}{PathBase}{Path}{QueryString} - {ContentType} {ContentLength}","@tr":"2d909872ae81ee72ca8b85a5103c8d17","@sp":"315540cfd6f66ec1","Protocol":"HTTP/1.1","Method":"GET","ContentType":null,"ContentLength":null,"Scheme":"http","Host":"localhost:5199","PathBase":"","Path":"/app.caorvekx4e.css","QueryString":"","EventId":{"Id":1},"SourceContext":"Microsoft.AspNetCore.Hosting.Diagnostics","RequestId":"0HNMKD15V5L5S:00000002","RequestPath":"/app.caorvekx4e.css","ConnectionId":"0HNMKD15V5L5S"}
{"@t":"2026-06-27T16:22:35.6088665Z","@mt":"Request starting {Protocol} {Method} {Scheme}://{Host}{PathBase}{Path}{QueryString} - {ContentType} {ContentLength}","@tr":"c9af20513de1e5a4e0baf91d140ad64b","@sp":"79878e962cdb4ddd","Protocol":"HTTP/1.1","Method":"GET","ContentType":null,"ContentLength":null,"Scheme":"http","Host":"localhost:5199","PathBase":"","Path":"/_framework/blazor.web.js","QueryString":"","EventId":{"Id":1},"SourceContext":"Microsoft.AspNetCore.Hosting.Diagnostics","RequestId":"0HNMKD15V5L5U:00000001","RequestPath":"/_framework/blazor.web.js","ConnectionId":"0HNMKD15V5L5U"}
{"@t":"2026-06-27T16:22:35.6088786Z","@mt":"Request starting {Protocol} {Method} {Scheme}://{Host}{PathBase}{Path}{QueryString} - {ContentType} {ContentLength}","@tr":"be777ec7f8c76521f2556327fd56c41d","@sp":"47f5aa54c904de9c","Protocol":"HTTP/1.1","Method":"GET","ContentType":null,"ContentLength":null,"Scheme":"http","Host":"localhost:5199","PathBase":"","Path":"/QueueIQ.Web.dvyq0oszyw.styles.css","QueryString":"","EventId":{"Id":1},"SourceContext":"Microsoft.AspNetCore.Hosting.Diagnostics","RequestId":"0HNMKD15V5L5T:00000001","RequestPath":"/QueueIQ.Web.dvyq0oszyw.styles.css","ConnectionId":"0HNMKD15V5L5T"}
{"@t":"2026-06-27T16:22:35.6115079Z","@mt":"Executing endpoint '{EndpointName}'","@tr":"c9af20513de1e5a4e0baf91d140ad64b","@sp":"79878e962cdb4ddd","EndpointName":"Blazor web static files","EventId":{"Name":"ExecutingEndpoint"},"SourceContext":"Microsoft.AspNetCore.Routing.EndpointMiddleware","RequestId":"0HNMKD15V5L5U:00000001","RequestPath":"/_framework/blazor.web.js","ConnectionId":"0HNMKD15V5L5U"}
{"@t":"2026-06-27T16:22:35.6123958Z","@mt":"Executing endpoint '{EndpointName}'","@tr":"2d909872ae81ee72ca8b85a5103c8d17","@sp":"315540cfd6f66ec1","EndpointName":"Microsoft.AspNetCore.Routing.RouteEndpoint","EventId":{"Name":"ExecutingEndpoint"},"SourceContext":"Microsoft.AspNetCore.Routing.EndpointMiddleware","RequestId":"0HNMKD15V5L5S:00000002","RequestPath":"/app.caorvekx4e.css","ConnectionId":"0HNMKD15V5L5S"}
{"@t":"2026-06-27T16:22:35.6124057Z","@mt":"Executing endpoint '{EndpointName}'","@tr":"be777ec7f8c76521f2556327fd56c41d","@sp":"47f5aa54c904de9c","EndpointName":"Microsoft.AspNetCore.Routing.RouteEndpoint","EventId":{"Name":"ExecutingEndpoint"},"SourceContext":"Microsoft.AspNetCore.Routing.EndpointMiddleware","RequestId":"0HNMKD15V5L5T:00000001","RequestPath":"/QueueIQ.Web.dvyq0oszyw.styles.css","ConnectionId":"0HNMKD15V5L5T"}
{"@t":"2026-06-27T16:22:35.6225742Z","@mt":"Sending file. Request path: '{VirtualPath}'. Physical path: '{PhysicalPath}'","@tr":"c9af20513de1e5a4e0baf91d140ad64b","@sp":"79878e962cdb4ddd","VirtualPath":"/_framework/blazor.web.js","PhysicalPath":"N/A","EventId":{"Id":2,"Name":"FileServed"},"SourceContext":"Microsoft.AspNetCore.StaticFiles.StaticFileMiddleware","RequestId":"0HNMKD15V5L5U:00000001","RequestPath":"/_framework/blazor.web.js","ConnectionId":"0HNMKD15V5L5U"}
{"@t":"2026-06-27T16:22:35.6227578Z","@mt":"Executed endpoint '{EndpointName}'","@tr":"c9af20513de1e5a4e0baf91d140ad64b","@sp":"79878e962cdb4ddd","EndpointName":"Blazor web static files","EventId":{"Id":1,"Name":"ExecutedEndpoint"},"SourceContext":"Microsoft.AspNetCore.Routing.EndpointMiddleware","RequestId":"0HNMKD15V5L5U:00000001","RequestPath":"/_framework/blazor.web.js","ConnectionId":"0HNMKD15V5L5U"}
{"@t":"2026-06-27T16:22:35.6373386Z","@mt":"Request finished {Protocol} {Method} {Scheme}://{Host}{PathBase}{Path}{QueryString} - {StatusCode} {ContentLength} {ContentType} {ElapsedMilliseconds}ms","@tr":"c9af20513de1e5a4e0baf91d140ad64b","@sp":"79878e962cdb4ddd","ElapsedMilliseconds":28.6551,"StatusCode":200,"ContentType":"text/javascript","ContentLength":187665,"Protocol":"HTTP/1.1","Method":"GET","Scheme":"http","Host":"localhost:5199","PathBase":"","Path":"/_framework/blazor.web.js","QueryString":"","EventId":{"Id":2},"SourceContext":"Microsoft.AspNetCore.Hosting.Diagnostics","RequestId":"0HNMKD15V5L5U:00000001","RequestPath":"/_framework/blazor.web.js","ConnectionId":"0HNMKD15V5L5U"}
{"@t":"2026-06-27T16:22:35.6383657Z","@mt":"Sending file. Request path: '{VirtualPath}'. Physical path: '{PhysicalPath}'","@tr":"be777ec7f8c76521f2556327fd56c41d","@sp":"47f5aa54c904de9c","VirtualPath":"QueueIQ.Web.dvyq0oszyw.styles.css","PhysicalPath":"C:\\Users\\Joseph\\Documents\\QueueIQ\\src\\QueueIQ.Web\\obj\\Debug\\net9.0\\compressed\\le3gd6ksss-dvyq0oszyw.gz","EventId":{"Id":2,"Name":"FileServed"},"SourceContext":"Microsoft.AspNetCore.StaticAssets.StaticAssetsInvoker","RequestId":"0HNMKD15V5L5T:00000001","RequestPath":"/QueueIQ.Web.dvyq0oszyw.styles.css","ConnectionId":"0HNMKD15V5L5T"}
{"@t":"2026-06-27T16:22:35.6385382Z","@mt":"Sending file. Request path: '{VirtualPath}'. Physical path: '{PhysicalPath}'","@tr":"2d909872ae81ee72ca8b85a5103c8d17","@sp":"315540cfd6f66ec1","VirtualPath":"app.caorvekx4e.css","PhysicalPath":"C:\\Users\\Joseph\\Documents\\QueueIQ\\src\\QueueIQ.Web\\obj\\Debug\\net9.0\\compressed\\jxu4ldg72n-caorvekx4e.gz","EventId":{"Id":2,"Name":"FileServed"},"SourceContext":"Microsoft.AspNetCore.StaticAssets.StaticAssetsInvoker","RequestId":"0HNMKD15V5L5S:00000002","RequestPath":"/app.caorvekx4e.css","ConnectionId":"0HNMKD15V5L5S"}
{"@t":"2026-06-27T16:22:35.6386308Z","@mt":"Executed endpoint '{EndpointName}'","@tr":"2d909872ae81ee72ca8b85a5103c8d17","@sp":"315540cfd6f66ec1","EndpointName":"Microsoft.AspNetCore.Routing.RouteEndpoint","EventId":{"Id":1,"Name":"ExecutedEndpoint"},"SourceContext":"Microsoft.AspNetCore.Routing.EndpointMiddleware","RequestId":"0HNMKD15V5L5S:00000002","RequestPath":"/app.caorvekx4e.css","ConnectionId":"0HNMKD15V5L5S"}
{"@t":"2026-06-27T16:22:35.6385684Z","@mt":"Executed endpoint '{EndpointName}'","@tr":"be777ec7f8c76521f2556327fd56c41d","@sp":"47f5aa54c904de9c","EndpointName":"Microsoft.AspNetCore.Routing.RouteEndpoint","EventId":{"Id":1,"Name":"ExecutedEndpoint"},"SourceContext":"Microsoft.AspNetCore.Routing.EndpointMiddleware","RequestId":"0HNMKD15V5L5T:00000001","RequestPath":"/QueueIQ.Web.dvyq0oszyw.styles.css","ConnectionId":"0HNMKD15V5L5T"}
{"@t":"2026-06-27T16:22:35.6388284Z","@mt":"Request finished {Protocol} {Method} {Scheme}://{Host}{PathBase}{Path}{QueryString} - {StatusCode} {ContentLength} {ContentType} {ElapsedMilliseconds}ms","@tr":"2d909872ae81ee72ca8b85a5103c8d17","@sp":"315540cfd6f66ec1","ElapsedMilliseconds":30.3339,"StatusCode":200,"ContentType":"text/css","ContentLength":4246,"Protocol":"HTTP/1.1","Method":"GET","Scheme":"http","Host":"localhost:5199","PathBase":"","Path":"/app.caorvekx4e.css","QueryString":"","EventId":{"Id":2},"SourceContext":"Microsoft.AspNetCore.Hosting.Diagnostics","RequestId":"0HNMKD15V5L5S:00000002","RequestPath":"/app.caorvekx4e.css","ConnectionId":"0HNMKD15V5L5S"}
{"@t":"2026-06-27T16:22:35.6389041Z","@mt":"Request finished {Protocol} {Method} {Scheme}://{Host}{PathBase}{Path}{QueryString} - {StatusCode} {ContentLength} {ContentType} {ElapsedMilliseconds}ms","@tr":"be777ec7f8c76521f2556327fd56c41d","@sp":"47f5aa54c904de9c","ElapsedMilliseconds":30.39,"StatusCode":200,"ContentType":"text/css","ContentLength":595,"Protocol":"HTTP/1.1","Method":"GET","Scheme":"http","Host":"localhost:5199","PathBase":"","Path":"/QueueIQ.Web.dvyq0oszyw.styles.css","QueryString":"","EventId":{"Id":2},"SourceContext":"Microsoft.AspNetCore.Hosting.Diagnostics","RequestId":"0HNMKD15V5L5T:00000001","RequestPath":"/QueueIQ.Web.dvyq0oszyw.styles.css","ConnectionId":"0HNMKD15V5L5T"}
{"@t":"2026-06-27T16:22:35.7856327Z","@mt":"Request starting {Protocol} {Method} {Scheme}://{Host}{PathBase}{Path}{QueryString} - {ContentType} {ContentLength}","@tr":"2e405de30bef585577cdf45cb5677f02","@sp":"e16453abcd2bb3c3","Protocol":"HTTP/1.1","Method":"GET","ContentType":null,"ContentLength":null,"Scheme":"http","Host":"localhost:5199","PathBase":"","Path":"/_blazor/initializers","QueryString":"","EventId":{"Id":1},"SourceContext":"Microsoft.AspNetCore.Hosting.Diagnostics","RequestId":"0HNMKD15V5L5S:00000003","RequestPath":"/_blazor/initializers","ConnectionId":"0HNMKD15V5L5S"}
{"@t":"2026-06-27T16:22:35.7860515Z","@mt":"Executing endpoint '{EndpointName}'","@tr":"2e405de30bef585577cdf45cb5677f02","@sp":"e16453abcd2bb3c3","EndpointName":"Microsoft.AspNetCore.Routing.RouteEndpoint","EventId":{"Name":"ExecutingEndpoint"},"SourceContext":"Microsoft.AspNetCore.Routing.EndpointMiddleware","RequestId":"0HNMKD15V5L5S:00000003","RequestPath":"/_blazor/initializers","ConnectionId":"0HNMKD15V5L5S"}
{"@t":"2026-06-27T16:22:35.7901059Z","@mt":"Executed endpoint '{EndpointName}'","@tr":"2e405de30bef585577cdf45cb5677f02","@sp":"e16453abcd2bb3c3","EndpointName":"Microsoft.AspNetCore.Routing.RouteEndpoint","EventId":{"Id":1,"Name":"ExecutedEndpoint"},"SourceContext":"Microsoft.AspNetCore.Routing.EndpointMiddleware","RequestId":"0HNMKD15V5L5S:00000003","RequestPath":"/_blazor/initializers","ConnectionId":"0HNMKD15V5L5S"}
{"@t":"2026-06-27T16:22:35.7902852Z","@mt":"Request finished {Protocol} {Method} {Scheme}://{Host}{PathBase}{Path}{QueryString} - {StatusCode} {ContentLength} {ContentType} {ElapsedMilliseconds}ms","@tr":"2e405de30bef585577cdf45cb5677f02","@sp":"e16453abcd2bb3c3","ElapsedMilliseconds":4.6564,"StatusCode":200,"ContentType":"application/json; charset=utf-8","ContentLength":null,"Protocol":"HTTP/1.1","Method":"GET","Scheme":"http","Host":"localhost:5199","PathBase":"","Path":"/_blazor/initializers","QueryString":"","EventId":{"Id":2},"SourceContext":"Microsoft.AspNetCore.Hosting.Diagnostics","RequestId":"0HNMKD15V5L5S:00000003","RequestPath":"/_blazor/initializers","ConnectionId":"0HNMKD15V5L5S"}
{"@t":"2026-06-27T16:22:35.8046372Z","@mt":"Request starting {Protocol} {Method} {Scheme}://{Host}{PathBase}{Path}{QueryString} - {ContentType} {ContentLength}","@tr":"d0565361f4c37304a9898edc5e84fd27","@sp":"b24fdd24fe615ff7","Protocol":"HTTP/1.1","Method":"POST","ContentType":null,"ContentLength":0,"Scheme":"http","Host":"localhost:5199","PathBase":"","Path":"/_blazor/negotiate","QueryString":"?negotiateVersion=1","EventId":{"Id":1},"SourceContext":"Microsoft.AspNetCore.Hosting.Diagnostics","RequestId":"0HNMKD15V5L5S:00000004","RequestPath":"/_blazor/negotiate","ConnectionId":"0HNMKD15V5L5S"}
{"@t":"2026-06-27T16:22:35.8053842Z","@mt":"Executing endpoint '{EndpointName}'","@tr":"d0565361f4c37304a9898edc5e84fd27","@sp":"b24fdd24fe615ff7","EndpointName":"Microsoft.AspNetCore.Routing.RouteEndpoint","EventId":{"Name":"ExecutingEndpoint"},"SourceContext":"Microsoft.AspNetCore.Routing.EndpointMiddleware","RequestId":"0HNMKD15V5L5S:00000004","RequestPath":"/_blazor/negotiate","ConnectionId":"0HNMKD15V5L5S"}
{"@t":"2026-06-27T16:22:35.8067949Z","@mt":"Request starting {Protocol} {Method} {Scheme}://{Host}{PathBase}{Path}{QueryString} - {ContentType} {ContentLength}","@tr":"0e3e54aa26f75a971bc958f70953f98c","@sp":"9e00963bf3b9ebd8","Protocol":"HTTP/1.1","Method":"GET","ContentType":null,"ContentLength":null,"Scheme":"http","Host":"localhost:5199","PathBase":"","Path":"/favicon.ico","QueryString":"","EventId":{"Id":1},"SourceContext":"Microsoft.AspNetCore.Hosting.Diagnostics","RequestId":"0HNMKD15V5L5T:00000002","RequestPath":"/favicon.ico","ConnectionId":"0HNMKD15V5L5T"}
{"@t":"2026-06-27T16:22:35.8076394Z","@mt":"Request finished {Protocol} {Method} {Scheme}://{Host}{PathBase}{Path}{QueryString} - {StatusCode} {ContentLength} {ContentType} {ElapsedMilliseconds}ms","@tr":"0e3e54aa26f75a971bc958f70953f98c","@sp":"9e00963bf3b9ebd8","ElapsedMilliseconds":0.8366,"StatusCode":404,"ContentType":null,"ContentLength":0,"Protocol":"HTTP/1.1","Method":"GET","Scheme":"http","Host":"localhost:5199","PathBase":"","Path":"/favicon.ico","QueryString":"","EventId":{"Id":2},"SourceContext":"Microsoft.AspNetCore.Hosting.Diagnostics","RequestId":"0HNMKD15V5L5T:00000002","RequestPath":"/favicon.ico","ConnectionId":"0HNMKD15V5L5T"}
{"@t":"2026-06-27T16:22:35.8080212Z","@mt":"Request reached the end of the middleware pipeline without being handled by application code. Request path: {Method} {Scheme}://{Host}{PathBase}{Path}, Response status code: {StatusCode}","@tr":"0e3e54aa26f75a971bc958f70953f98c","@sp":"9e00963bf3b9ebd8","Method":"GET","Scheme":"http","Host":"localhost:5199","PathBase":"","Path":"/favicon.ico","StatusCode":404,"EventId":{"Id":16},"SourceContext":"Microsoft.AspNetCore.Hosting.Diagnostics","RequestId":"0HNMKD15V5L5T:00000002","RequestPath":"/favicon.ico","ConnectionId":"0HNMKD15V5L5T"}
{"@t":"2026-06-27T16:22:35.8132039Z","@mt":"Executed endpoint '{EndpointName}'","@tr":"d0565361f4c37304a9898edc5e84fd27","@sp":"b24fdd24fe615ff7","EndpointName":"Microsoft.AspNetCore.Routing.RouteEndpoint","EventId":{"Id":1,"Name":"ExecutedEndpoint"},"SourceContext":"Microsoft.AspNetCore.Routing.EndpointMiddleware","RequestId":"0HNMKD15V5L5S:00000004","RequestPath":"/_blazor/negotiate","ConnectionId":"0HNMKD15V5L5S"}
{"@t":"2026-06-27T16:22:35.8133682Z","@mt":"Request finished {Protocol} {Method} {Scheme}://{Host}{PathBase}{Path}{QueryString} - {StatusCode} {ContentLength} {ContentType} {ElapsedMilliseconds}ms","@tr":"d0565361f4c37304a9898edc5e84fd27","@sp":"b24fdd24fe615ff7","ElapsedMilliseconds":8.7361,"StatusCode":200,"ContentType":"application/json","ContentLength":316,"Protocol":"HTTP/1.1","Method":"POST","Scheme":"http","Host":"localhost:5199","PathBase":"","Path":"/_blazor/negotiate","QueryString":"?negotiateVersion=1","EventId":{"Id":2},"SourceContext":"Microsoft.AspNetCore.Hosting.Diagnostics","RequestId":"0HNMKD15V5L5S:00000004","RequestPath":"/_blazor/negotiate","ConnectionId":"0HNMKD15V5L5S"}
{"@t":"2026-06-27T16:45:08.3508964Z","@mt":"User profile is available. Using '{FullName}' as key repository and Windows DPAPI to encrypt keys at rest.","FullName":"C:\\Users\\Joseph\\AppData\\Local\\ASP.NET\\DataProtection-Keys","EventId":{"Id":63,"Name":"UsingProfileAsKeyRepositoryWithDPAPI"},"SourceContext":"Microsoft.AspNetCore.DataProtection.KeyManagement.XmlKeyManager"}
{"@t":"2026-06-27T16:45:09.0996361Z","@mt":"Now listening on: {address}","address":"http://localhost:5199","EventId":{"Id":14,"Name":"ListeningOnAddress"},"SourceContext":"Microsoft.Hosting.Lifetime"}
{"@t":"2026-06-27T16:45:09.1026841Z","@mt":"Application started. Press Ctrl+C to shut down.","SourceContext":"Microsoft.Hosting.Lifetime"}
{"@t":"2026-06-27T16:45:09.1030604Z","@mt":"Hosting environment: {EnvName}","EnvName":"Development","SourceContext":"Microsoft.Hosting.Lifetime"}
{"@t":"2026-06-27T16:45:09.1031268Z","@mt":"Content root path: {ContentRoot}","ContentRoot":"C:\\Users\\Joseph\\Documents\\QueueIQ\\src\\QueueIQ.Web","SourceContext":"Microsoft.Hosting.Lifetime"}
{"@t":"2026-06-27T16:45:11.6245302Z","@mt":"Request starting {Protocol} {Method} {Scheme}://{Host}{PathBase}{Path}{QueryString} - {ContentType} {ContentLength}","@tr":"d5d2cdd343def060eee585084c04e8f8","@sp":"87391079ff479731","Protocol":"HTTP/1.1","Method":"GET","ContentType":null,"ContentLength":null,"Scheme":"http","Host":"localhost:5199","PathBase":"","Path":"/join/joes-barbershop","QueryString":"","EventId":{"Id":1},"SourceContext":"Microsoft.AspNetCore.Hosting.Diagnostics","RequestId":"0HNMKDDQ9IJOM:00000001","RequestPath":"/join/joes-barbershop","ConnectionId":"0HNMKDDQ9IJOM"}
{"@t":"2026-06-27T16:45:11.6461753Z","@mt":"Failed to determine the https port for redirect.","@l":"Warning","@tr":"d5d2cdd343def060eee585084c04e8f8","@sp":"87391079ff479731","EventId":{"Id":3,"Name":"FailedToDeterminePort"},"SourceContext":"Microsoft.AspNetCore.HttpsPolicy.HttpsRedirectionMiddleware","RequestId":"0HNMKDDQ9IJOM:00000001","RequestPath":"/join/joes-barbershop","ConnectionId":"0HNMKDDQ9IJOM"}
{"@t":"2026-06-27T16:45:11.6478369Z","@mt":"Executing endpoint '{EndpointName}'","@tr":"d5d2cdd343def060eee585084c04e8f8","@sp":"87391079ff479731","EndpointName":"/join/{Slug} (/join/{Slug})","EventId":{"Name":"ExecutingEndpoint"},"SourceContext":"Microsoft.AspNetCore.Routing.EndpointMiddleware","RequestId":"0HNMKDDQ9IJOM:00000001","RequestPath":"/join/joes-barbershop","ConnectionId":"0HNMKDDQ9IJOM"}
{"@t":"2026-06-27T16:45:11.6984543Z","@mt":"Start processing HTTP request {HttpMethod} {Uri}","@tr":"d5d2cdd343def060eee585084c04e8f8","@sp":"87391079ff479731","HttpMethod":"GET","Uri":"http://localhost:5088/api/businesses/joes-barbershop","EventId":{"Id":100,"Name":"RequestPipelineStart"},"SourceContext":"System.Net.Http.HttpClient.ApiClient.LogicalHandler","RequestId":"0HNMKDDQ9IJOM:00000001","RequestPath":"/join/joes-barbershop","ConnectionId":"0HNMKDDQ9IJOM","Scope":["HTTP GET http://localhost:5088/api/businesses/joes-barbershop"]}
{"@t":"2026-06-27T16:45:11.7002835Z","@mt":"Sending HTTP request {HttpMethod} {Uri}","@tr":"d5d2cdd343def060eee585084c04e8f8","@sp":"87391079ff479731","HttpMethod":"GET","Uri":"http://localhost:5088/api/businesses/joes-barbershop","EventId":{"Id":100,"Name":"RequestStart"},"SourceContext":"System.Net.Http.HttpClient.ApiClient.ClientHandler","RequestId":"0HNMKDDQ9IJOM:00000001","RequestPath":"/join/joes-barbershop","ConnectionId":"0HNMKDDQ9IJOM","Scope":["HTTP GET http://localhost:5088/api/businesses/joes-barbershop"]}
{"@t":"2026-06-27T16:45:12.1264293Z","@mt":"Received HTTP response headers after {ElapsedMilliseconds}ms - {StatusCode}","@tr":"d5d2cdd343def060eee585084c04e8f8","@sp":"87391079ff479731","ElapsedMilliseconds":424.4323,"StatusCode":200,"EventId":{"Id":101,"Name":"RequestEnd"},"SourceContext":"System.Net.Http.HttpClient.ApiClient.ClientHandler","HttpMethod":"GET","Uri":"http://localhost:5088/api/businesses/joes-barbershop","RequestId":"0HNMKDDQ9IJOM:00000001","RequestPath":"/join/joes-barbershop","ConnectionId":"0HNMKDDQ9IJOM","Scope":["HTTP GET http://localhost:5088/api/businesses/joes-barbershop"]}
{"@t":"2026-06-27T16:45:12.1340770Z","@mt":"End processing HTTP request after {ElapsedMilliseconds}ms - {StatusCode}","@tr":"d5d2cdd343def060eee585084c04e8f8","@sp":"87391079ff479731","ElapsedMilliseconds":437.6588,"StatusCode":200,"EventId":{"Id":101,"Name":"RequestPipelineEnd"},"SourceContext":"System.Net.Http.HttpClient.ApiClient.LogicalHandler","HttpMethod":"GET","Uri":"http://localhost:5088/api/businesses/joes-barbershop","RequestId":"0HNMKDDQ9IJOM:00000001","RequestPath":"/join/joes-barbershop","ConnectionId":"0HNMKDDQ9IJOM","Scope":["HTTP GET http://localhost:5088/api/businesses/joes-barbershop"]}
{"@t":"2026-06-27T16:45:12.2187260Z","@mt":"Executed endpoint '{EndpointName}'","@tr":"d5d2cdd343def060eee585084c04e8f8","@sp":"87391079ff479731","EndpointName":"/join/{Slug} (/join/{Slug})","EventId":{"Id":1,"Name":"ExecutedEndpoint"},"SourceContext":"Microsoft.AspNetCore.Routing.EndpointMiddleware","RequestId":"0HNMKDDQ9IJOM:00000001","RequestPath":"/join/joes-barbershop","ConnectionId":"0HNMKDDQ9IJOM"}
{"@t":"2026-06-27T16:45:12.2222068Z","@mt":"Request finished {Protocol} {Method} {Scheme}://{Host}{PathBase}{Path}{QueryString} - {StatusCode} {ContentLength} {ContentType} {ElapsedMilliseconds}ms","@tr":"d5d2cdd343def060eee585084c04e8f8","@sp":"87391079ff479731","ElapsedMilliseconds":598.83,"StatusCode":200,"ContentType":"text/html; charset=utf-8","ContentLength":null,"Protocol":"HTTP/1.1","Method":"GET","Scheme":"http","Host":"localhost:5199","PathBase":"","Path":"/join/joes-barbershop","QueryString":"","EventId":{"Id":2},"SourceContext":"Microsoft.AspNetCore.Hosting.Diagnostics","RequestId":"0HNMKDDQ9IJOM:00000001","RequestPath":"/join/joes-barbershop","ConnectionId":"0HNMKDDQ9IJOM"}
{"@t":"2026-06-27T16:45:12.2372463Z","@mt":"Request starting {Protocol} {Method} {Scheme}://{Host}{PathBase}{Path}{QueryString} - {ContentType} {ContentLength}","@tr":"d47456b8670bf9471a566cacaa72d51f","@sp":"e5f68e891ffec377","Protocol":"HTTP/1.1","Method":"GET","ContentType":null,"ContentLength":null,"Scheme":"http","Host":"localhost:5199","PathBase":"","Path":"/app.9msw5ztgru.css","QueryString":"","EventId":{"Id":1},"SourceContext":"Microsoft.AspNetCore.Hosting.Diagnostics","RequestId":"0HNMKDDQ9IJOM:00000002","RequestPath":"/app.9msw5ztgru.css","ConnectionId":"0HNMKDDQ9IJOM"}
{"@t":"2026-06-27T16:45:12.2372417Z","@mt":"Request starting {Protocol} {Method} {Scheme}://{Host}{PathBase}{Path}{QueryString} - {ContentType} {ContentLength}","@tr":"192facbb179186bbba8cf1a8d512ec5c","@sp":"219be64c4a7d20a7","Protocol":"HTTP/1.1","Method":"GET","ContentType":null,"ContentLength":null,"Scheme":"http","Host":"localhost:5199","PathBase":"","Path":"/_framework/blazor.web.js","QueryString":"","EventId":{"Id":1},"SourceContext":"Microsoft.AspNetCore.Hosting.Diagnostics","RequestId":"0HNMKDDQ9IJOO:00000001","RequestPath":"/_framework/blazor.web.js","ConnectionId":"0HNMKDDQ9IJOO"}
{"@t":"2026-06-27T16:45:12.2372350Z","@mt":"Request starting {Protocol} {Method} {Scheme}://{Host}{PathBase}{Path}{QueryString} - {ContentType} {ContentLength}","@tr":"fd609350a6533ffefe9820451a38293e","@sp":"cf9adef92f10a201","Protocol":"HTTP/1.1","Method":"GET","ContentType":null,"ContentLength":null,"Scheme":"http","Host":"localhost:5199","PathBase":"","Path":"/QueueIQ.Web.dvyq0oszyw.styles.css","QueryString":"","EventId":{"Id":1},"SourceContext":"Microsoft.AspNetCore.Hosting.Diagnostics","RequestId":"0HNMKDDQ9IJON:00000001","RequestPath":"/QueueIQ.Web.dvyq0oszyw.styles.css","ConnectionId":"0HNMKDDQ9IJON"}
{"@t":"2026-06-27T16:45:12.2402550Z","@mt":"Executing endpoint '{EndpointName}'","@tr":"192facbb179186bbba8cf1a8d512ec5c","@sp":"219be64c4a7d20a7","EndpointName":"Blazor web static files","EventId":{"Name":"ExecutingEndpoint"},"SourceContext":"Microsoft.AspNetCore.Routing.EndpointMiddleware","RequestId":"0HNMKDDQ9IJOO:00000001","RequestPath":"/_framework/blazor.web.js","ConnectionId":"0HNMKDDQ9IJOO"}
{"@t":"2026-06-27T16:45:12.2412925Z","@mt":"Executing endpoint '{EndpointName}'","@tr":"fd609350a6533ffefe9820451a38293e","@sp":"cf9adef92f10a201","EndpointName":"Microsoft.AspNetCore.Routing.RouteEndpoint","EventId":{"Name":"ExecutingEndpoint"},"SourceContext":"Microsoft.AspNetCore.Routing.EndpointMiddleware","RequestId":"0HNMKDDQ9IJON:00000001","RequestPath":"/QueueIQ.Web.dvyq0oszyw.styles.css","ConnectionId":"0HNMKDDQ9IJON"}
{"@t":"2026-06-27T16:45:12.2412925Z","@mt":"Executing endpoint '{EndpointName}'","@tr":"d47456b8670bf9471a566cacaa72d51f","@sp":"e5f68e891ffec377","EndpointName":"Microsoft.AspNetCore.Routing.RouteEndpoint","EventId":{"Name":"ExecutingEndpoint"},"SourceContext":"Microsoft.AspNetCore.Routing.EndpointMiddleware","RequestId":"0HNMKDDQ9IJOM:00000002","RequestPath":"/app.9msw5ztgru.css","ConnectionId":"0HNMKDDQ9IJOM"}
{"@t":"2026-06-27T16:45:12.2437193Z","@mt":"The file {Path} was not modified","@tr":"192facbb179186bbba8cf1a8d512ec5c","@sp":"219be64c4a7d20a7","Path":"/_framework/blazor.web.js","EventId":{"Id":6,"Name":"FileNotModified"},"SourceContext":"Microsoft.AspNetCore.StaticFiles.StaticFileMiddleware","RequestId":"0HNMKDDQ9IJOO:00000001","RequestPath":"/_framework/blazor.web.js","ConnectionId":"0HNMKDDQ9IJOO"}
{"@t":"2026-06-27T16:45:12.2440683Z","@mt":"Executed endpoint '{EndpointName}'","@tr":"192facbb179186bbba8cf1a8d512ec5c","@sp":"219be64c4a7d20a7","EndpointName":"Blazor web static files","EventId":{"Id":1,"Name":"ExecutedEndpoint"},"SourceContext":"Microsoft.AspNetCore.Routing.EndpointMiddleware","RequestId":"0HNMKDDQ9IJOO:00000001","RequestPath":"/_framework/blazor.web.js","ConnectionId":"0HNMKDDQ9IJOO"}
{"@t":"2026-06-27T16:45:12.2442543Z","@mt":"Request finished {Protocol} {Method} {Scheme}://{Host}{PathBase}{Path}{QueryString} - {StatusCode} {ContentLength} {ContentType} {ElapsedMilliseconds}ms","@tr":"192facbb179186bbba8cf1a8d512ec5c","@sp":"219be64c4a7d20a7","ElapsedMilliseconds":7.3354,"StatusCode":304,"ContentType":"text/javascript","ContentLength":null,"Protocol":"HTTP/1.1","Method":"GET","Scheme":"http","Host":"localhost:5199","PathBase":"","Path":"/_framework/blazor.web.js","QueryString":"","EventId":{"Id":2},"SourceContext":"Microsoft.AspNetCore.Hosting.Diagnostics","RequestId":"0HNMKDDQ9IJOO:00000001","RequestPath":"/_framework/blazor.web.js","ConnectionId":"0HNMKDDQ9IJOO"}
{"@t":"2026-06-27T16:45:12.2525471Z","@mt":"Sending file. Request path: '{VirtualPath}'. Physical path: '{PhysicalPath}'","@tr":"fd609350a6533ffefe9820451a38293e","@sp":"cf9adef92f10a201","VirtualPath":"QueueIQ.Web.dvyq0oszyw.styles.css","PhysicalPath":"C:\\Users\\Joseph\\Documents\\QueueIQ\\src\\QueueIQ.Web\\obj\\Debug\\net9.0\\compressed\\le3gd6ksss-dvyq0oszyw.gz","EventId":{"Id":2,"Name":"FileServed"},"SourceContext":"Microsoft.AspNetCore.StaticAssets.StaticAssetsInvoker","RequestId":"0HNMKDDQ9IJON:00000001","RequestPath":"/QueueIQ.Web.dvyq0oszyw.styles.css","ConnectionId":"0HNMKDDQ9IJON"}
{"@t":"2026-06-27T16:45:12.2526527Z","@mt":"Sending file. Request path: '{VirtualPath}'. Physical path: '{PhysicalPath}'","@tr":"d47456b8670bf9471a566cacaa72d51f","@sp":"e5f68e891ffec377","VirtualPath":"app.9msw5ztgru.css","PhysicalPath":"C:\\Users\\Joseph\\Documents\\QueueIQ\\src\\QueueIQ.Web\\obj\\Debug\\net9.0\\compressed\\jxu4ldg72n-9msw5ztgru.gz","EventId":{"Id":2,"Name":"FileServed"},"SourceContext":"Microsoft.AspNetCore.StaticAssets.StaticAssetsInvoker","RequestId":"0HNMKDDQ9IJOM:00000002","RequestPath":"/app.9msw5ztgru.css","ConnectionId":"0HNMKDDQ9IJOM"}
{"@t":"2026-06-27T16:45:12.2528876Z","@mt":"Executed endpoint '{EndpointName}'","@tr":"fd609350a6533ffefe9820451a38293e","@sp":"cf9adef92f10a201","EndpointName":"Microsoft.AspNetCore.Routing.RouteEndpoint","EventId":{"Id":1,"Name":"ExecutedEndpoint"},"SourceContext":"Microsoft.AspNetCore.Routing.EndpointMiddleware","RequestId":"0HNMKDDQ9IJON:00000001","RequestPath":"/QueueIQ.Web.dvyq0oszyw.styles.css","ConnectionId":"0HNMKDDQ9IJON"}
{"@t":"2026-06-27T16:45:12.2529084Z","@mt":"Executed endpoint '{EndpointName}'","@tr":"d47456b8670bf9471a566cacaa72d51f","@sp":"e5f68e891ffec377","EndpointName":"Microsoft.AspNetCore.Routing.RouteEndpoint","EventId":{"Id":1,"Name":"ExecutedEndpoint"},"SourceContext":"Microsoft.AspNetCore.Routing.EndpointMiddleware","RequestId":"0HNMKDDQ9IJOM:00000002","RequestPath":"/app.9msw5ztgru.css","ConnectionId":"0HNMKDDQ9IJOM"}
{"@t":"2026-06-27T16:45:12.2530656Z","@mt":"Request finished {Protocol} {Method} {Scheme}://{Host}{PathBase}{Path}{QueryString} - {StatusCode} {ContentLength} {ContentType} {ElapsedMilliseconds}ms","@tr":"fd609350a6533ffefe9820451a38293e","@sp":"cf9adef92f10a201","ElapsedMilliseconds":16.138,"StatusCode":200,"ContentType":"text/css","ContentLength":595,"Protocol":"HTTP/1.1","Method":"GET","Scheme":"http","Host":"localhost:5199","PathBase":"","Path":"/QueueIQ.Web.dvyq0oszyw.styles.css","QueryString":"","EventId":{"Id":2},"SourceContext":"Microsoft.AspNetCore.Hosting.Diagnostics","RequestId":"0HNMKDDQ9IJON:00000001","RequestPath":"/QueueIQ.Web.dvyq0oszyw.styles.css","ConnectionId":"0HNMKDDQ9IJON"}
{"@t":"2026-06-27T16:45:12.2530656Z","@mt":"Request finished {Protocol} {Method} {Scheme}://{Host}{PathBase}{Path}{QueryString} - {StatusCode} {ContentLength} {ContentType} {ElapsedMilliseconds}ms","@tr":"d47456b8670bf9471a566cacaa72d51f","@sp":"e5f68e891ffec377","ElapsedMilliseconds":16.1373,"StatusCode":200,"ContentType":"text/css","ContentLength":5705,"Protocol":"HTTP/1.1","Method":"GET","Scheme":"http","Host":"localhost:5199","PathBase":"","Path":"/app.9msw5ztgru.css","QueryString":"","EventId":{"Id":2},"SourceContext":"Microsoft.AspNetCore.Hosting.Diagnostics","RequestId":"0HNMKDDQ9IJOM:00000002","RequestPath":"/app.9msw5ztgru.css","ConnectionId":"0HNMKDDQ9IJOM"}
{"@t":"2026-06-27T16:45:12.3547457Z","@mt":"Request starting {Protocol} {Method} {Scheme}://{Host}{PathBase}{Path}{QueryString} - {ContentType} {ContentLength}","@tr":"7b6a608073dc126ab28615f6ea4b5313","@sp":"ab20e5d1e3700eac","Protocol":"HTTP/1.1","Method":"GET","ContentType":null,"ContentLength":null,"Scheme":"http","Host":"localhost:5199","PathBase":"","Path":"/_blazor/initializers","QueryString":"","EventId":{"Id":1},"SourceContext":"Microsoft.AspNetCore.Hosting.Diagnostics","RequestId":"0HNMKDDQ9IJOM:00000003","RequestPath":"/_blazor/initializers","ConnectionId":"0HNMKDDQ9IJOM"}
{"@t":"2026-06-27T16:45:12.3553610Z","@mt":"Executing endpoint '{EndpointName}'","@tr":"7b6a608073dc126ab28615f6ea4b5313","@sp":"ab20e5d1e3700eac","EndpointName":"Microsoft.AspNetCore.Routing.RouteEndpoint","EventId":{"Name":"ExecutingEndpoint"},"SourceContext":"Microsoft.AspNetCore.Routing.EndpointMiddleware","RequestId":"0HNMKDDQ9IJOM:00000003","RequestPath":"/_blazor/initializers","ConnectionId":"0HNMKDDQ9IJOM"}
{"@t":"2026-06-27T16:45:12.3599118Z","@mt":"Executed endpoint '{EndpointName}'","@tr":"7b6a608073dc126ab28615f6ea4b5313","@sp":"ab20e5d1e3700eac","EndpointName":"Microsoft.AspNetCore.Routing.RouteEndpoint","EventId":{"Id":1,"Name":"ExecutedEndpoint"},"SourceContext":"Microsoft.AspNetCore.Routing.EndpointMiddleware","RequestId":"0HNMKDDQ9IJOM:00000003","RequestPath":"/_blazor/initializers","ConnectionId":"0HNMKDDQ9IJOM"}
{"@t":"2026-06-27T16:45:12.3601710Z","@mt":"Request finished {Protocol} {Method} {Scheme}://{Host}{PathBase}{Path}{QueryString} - {StatusCode} {ContentLength} {ContentType} {ElapsedMilliseconds}ms","@tr":"7b6a608073dc126ab28615f6ea4b5313","@sp":"ab20e5d1e3700eac","ElapsedMilliseconds":5.4425,"StatusCode":200,"ContentType":"application/json; charset=utf-8","ContentLength":null,"Protocol":"HTTP/1.1","Method":"GET","Scheme":"http","Host":"localhost:5199","PathBase":"","Path":"/_blazor/initializers","QueryString":"","EventId":{"Id":2},"SourceContext":"Microsoft.AspNetCore.Hosting.Diagnostics","RequestId":"0HNMKDDQ9IJOM:00000003","RequestPath":"/_blazor/initializers","ConnectionId":"0HNMKDDQ9IJOM"}
{"@t":"2026-06-27T16:45:12.3684871Z","@mt":"Request starting {Protocol} {Method} {Scheme}://{Host}{PathBase}{Path}{QueryString} - {ContentType} {ContentLength}","@tr":"e69d5aeff608af464d1135685912b5bd","@sp":"a7ebc95490a7ecc3","Protocol":"HTTP/1.1","Method":"POST","ContentType":null,"ContentLength":0,"Scheme":"http","Host":"localhost:5199","PathBase":"","Path":"/_blazor/negotiate","QueryString":"?negotiateVersion=1","EventId":{"Id":1},"SourceContext":"Microsoft.AspNetCore.Hosting.Diagnostics","RequestId":"0HNMKDDQ9IJOM:00000004","RequestPath":"/_blazor/negotiate","ConnectionId":"0HNMKDDQ9IJOM"}
{"@t":"2026-06-27T16:45:12.3749024Z","@mt":"Executing endpoint '{EndpointName}'","@tr":"e69d5aeff608af464d1135685912b5bd","@sp":"a7ebc95490a7ecc3","EndpointName":"Microsoft.AspNetCore.Routing.RouteEndpoint","EventId":{"Name":"ExecutingEndpoint"},"SourceContext":"Microsoft.AspNetCore.Routing.EndpointMiddleware","RequestId":"0HNMKDDQ9IJOM:00000004","RequestPath":"/_blazor/negotiate","ConnectionId":"0HNMKDDQ9IJOM"}
{"@t":"2026-06-27T16:45:30.3252182Z","@mt":"Request starting {Protocol} {Method} {Scheme}://{Host}{PathBase}{Path}{QueryString} - {ContentType} {ContentLength}","@tr":"051da08c376a318135f414a621560b67","@sp":"6306551aaa02d548","Protocol":"HTTP/1.1","Method":"GET","ContentType":null,"ContentLength":null,"Scheme":"http","Host":"localhost:5199","PathBase":"","Path":"/join/joes-barbershop","QueryString":"","EventId":{"Id":1},"SourceContext":"Microsoft.AspNetCore.Hosting.Diagnostics","RequestId":"0HNMKDDQ9IJOO:00000002","RequestPath":"/join/joes-barbershop","ConnectionId":"0HNMKDDQ9IJOO"}
{"@t":"2026-06-27T16:45:12.4292510Z","@mt":"Request starting {Protocol} {Method} {Scheme}://{Host}{PathBase}{Path}{QueryString} - {ContentType} {ContentLength}","@tr":"5c9405e32814aa4722d5488528dde4dc","@sp":"c90d94829cbf2b94","Protocol":"HTTP/1.1","Method":"GET","ContentType":null,"ContentLength":null,"Scheme":"http","Host":"localhost:5199","PathBase":"","Path":"/favicon.ico","QueryString":"","EventId":{"Id":1},"SourceContext":"Microsoft.AspNetCore.Hosting.Diagnostics","RequestId":"0HNMKDDQ9IJON:00000002","RequestPath":"/favicon.ico","ConnectionId":"0HNMKDDQ9IJON"}
{"@t":"2026-06-27T16:45:45.5111928Z","@mt":"Request starting {Protocol} {Method} {Scheme}://{Host}{PathBase}{Path}{QueryString} - {ContentType} {ContentLength}","@tr":"6d9c4cd39083b570bd53e1e73e59d5c2","@sp":"078e95f8234fa121","Protocol":"HTTP/1.1","Method":"GET","ContentType":null,"ContentLength":null,"Scheme":"http","Host":"localhost:5199","PathBase":"","Path":"/staff/joes-barbershop","QueryString":"","EventId":{"Id":1},"SourceContext":"Microsoft.AspNetCore.Hosting.Diagnostics","RequestId":"0HNMKDDQ9IJOP:00000001","RequestPath":"/staff/joes-barbershop","ConnectionId":"0HNMKDDQ9IJOP"}
{"@t":"2026-06-27T16:46:02.9741027Z","@mt":"Request starting {Protocol} {Method} {Scheme}://{Host}{PathBase}{Path}{QueryString} - {ContentType} {ContentLength}","@tr":"ee659ee25ee2aad8b84be9fcd74ef6e0","@sp":"62d64e9dcfcf78d8","Protocol":"HTTP/1.1","Method":"GET","ContentType":null,"ContentLength":null,"Scheme":"http","Host":"localhost:5199","PathBase":"","Path":"/staff/joes-barbershop","QueryString":"","EventId":{"Id":1},"SourceContext":"Microsoft.AspNetCore.Hosting.Diagnostics","RequestId":"0HNMKDDQ9IJOQ:00000001","RequestPath":"/staff/joes-barbershop","ConnectionId":"0HNMKDDQ9IJOQ"}
{"@t":"2026-06-27T16:46:23.4990333Z","@mt":"Request starting {Protocol} {Method} {Scheme}://{Host}{PathBase}{Path}{QueryString} - {ContentType} {ContentLength}","@tr":"06ce8ac9184d06e0eae4eb29982e924a","@sp":"10a3dd9eb20f424d","Protocol":"HTTP/1.1","Method":"GET","ContentType":null,"ContentLength":null,"Scheme":"http","Host":"localhost:5199","PathBase":"","Path":"/join/joes-barbershop","QueryString":"","EventId":{"Id":1},"SourceContext":"Microsoft.AspNetCore.Hosting.Diagnostics","RequestId":"0HNMKDDQ9IJOR:00000001","RequestPath":"/join/joes-barbershop","ConnectionId":"0HNMKDDQ9IJOR"}
{"@t":"2026-06-27T16:46:39.0090716Z","@mt":"Executing endpoint '{EndpointName}'","@tr":"051da08c376a318135f414a621560b67","@sp":"6306551aaa02d548","EndpointName":"/join/{Slug} (/join/{Slug})","EventId":{"Name":"ExecutingEndpoint"},"SourceContext":"Microsoft.AspNetCore.Routing.EndpointMiddleware","RequestId":"0HNMKDDQ9IJOO:00000002","RequestPath":"/join/joes-barbershop","ConnectionId":"0HNMKDDQ9IJOO"}
{"@t":"2026-06-27T16:46:39.0090769Z","@mt":"Executing endpoint '{EndpointName}'","@tr":"ee659ee25ee2aad8b84be9fcd74ef6e0","@sp":"62d64e9dcfcf78d8","EndpointName":"/staff/{Slug} (/staff/{Slug})","EventId":{"Name":"ExecutingEndpoint"},"SourceContext":"Microsoft.AspNetCore.Routing.EndpointMiddleware","RequestId":"0HNMKDDQ9IJOQ:00000001","RequestPath":"/staff/joes-barbershop","ConnectionId":"0HNMKDDQ9IJOQ"}
{"@t":"2026-06-27T16:46:39.0090734Z","@mt":"Executing endpoint '{EndpointName}'","@tr":"06ce8ac9184d06e0eae4eb29982e924a","@sp":"10a3dd9eb20f424d","EndpointName":"/join/{Slug} (/join/{Slug})","EventId":{"Name":"ExecutingEndpoint"},"SourceContext":"Microsoft.AspNetCore.Routing.EndpointMiddleware","RequestId":"0HNMKDDQ9IJOR:00000001","RequestPath":"/join/joes-barbershop","ConnectionId":"0HNMKDDQ9IJOR"}
{"@t":"2026-06-27T16:46:39.0090716Z","@mt":"Executing endpoint '{EndpointName}'","@tr":"6d9c4cd39083b570bd53e1e73e59d5c2","@sp":"078e95f8234fa121","EndpointName":"/staff/{Slug} (/staff/{Slug})","EventId":{"Name":"ExecutingEndpoint"},"SourceContext":"Microsoft.AspNetCore.Routing.EndpointMiddleware","RequestId":"0HNMKDDQ9IJOP:00000001","RequestPath":"/staff/joes-barbershop","ConnectionId":"0HNMKDDQ9IJOP"}
{"@t":"2026-06-27T16:46:39.0094491Z","@mt":"Request finished {Protocol} {Method} {Scheme}://{Host}{PathBase}{Path}{QueryString} - {StatusCode} {ContentLength} {ContentType} {ElapsedMilliseconds}ms","@tr":"5c9405e32814aa4722d5488528dde4dc","@sp":"c90d94829cbf2b94","ElapsedMilliseconds":86580.1957,"StatusCode":499,"ContentType":null,"ContentLength":null,"Protocol":"HTTP/1.1","Method":"GET","Scheme":"http","Host":"localhost:5199","PathBase":"","Path":"/favicon.ico","QueryString":"","EventId":{"Id":2},"SourceContext":"Microsoft.AspNetCore.Hosting.Diagnostics","RequestId":"0HNMKDDQ9IJON:00000002","RequestPath":"/favicon.ico","ConnectionId":"0HNMKDDQ9IJON"}
{"@t":"2026-06-27T16:46:39.0097093Z","@mt":"Request reached the end of the middleware pipeline without being handled by application code. Request path: {Method} {Scheme}://{Host}{PathBase}{Path}, Response status code: {StatusCode}","@tr":"5c9405e32814aa4722d5488528dde4dc","@sp":"c90d94829cbf2b94","Method":"GET","Scheme":"http","Host":"localhost:5199","PathBase":"","Path":"/favicon.ico","StatusCode":499,"EventId":{"Id":16},"SourceContext":"Microsoft.AspNetCore.Hosting.Diagnostics","RequestId":"0HNMKDDQ9IJON:00000002","RequestPath":"/favicon.ico","ConnectionId":"0HNMKDDQ9IJON"}
{"@t":"2026-06-27T16:46:39.0137862Z","@mt":"Start processing HTTP request {HttpMethod} {Uri}","@tr":"06ce8ac9184d06e0eae4eb29982e924a","@sp":"10a3dd9eb20f424d","HttpMethod":"GET","Uri":"http://localhost:5088/api/businesses/joes-barbershop","EventId":{"Id":100,"Name":"RequestPipelineStart"},"SourceContext":"System.Net.Http.HttpClient.ApiClient.LogicalHandler","RequestId":"0HNMKDDQ9IJOR:00000001","RequestPath":"/join/joes-barbershop","ConnectionId":"0HNMKDDQ9IJOR","Scope":["HTTP GET http://localhost:5088/api/businesses/joes-barbershop"]}
{"@t":"2026-06-27T16:46:39.0137862Z","@mt":"Start processing HTTP request {HttpMethod} {Uri}","@tr":"051da08c376a318135f414a621560b67","@sp":"6306551aaa02d548","HttpMethod":"GET","Uri":"http://localhost:5088/api/businesses/joes-barbershop","EventId":{"Id":100,"Name":"RequestPipelineStart"},"SourceContext":"System.Net.Http.HttpClient.ApiClient.LogicalHandler","RequestId":"0HNMKDDQ9IJOO:00000002","RequestPath":"/join/joes-barbershop","ConnectionId":"0HNMKDDQ9IJOO","Scope":["HTTP GET http://localhost:5088/api/businesses/joes-barbershop"]}
{"@t":"2026-06-27T16:46:39.0139013Z","@mt":"Sending HTTP request {HttpMethod} {Uri}","@tr":"06ce8ac9184d06e0eae4eb29982e924a","@sp":"10a3dd9eb20f424d","HttpMethod":"GET","Uri":"http://localhost:5088/api/businesses/joes-barbershop","EventId":{"Id":100,"Name":"RequestStart"},"SourceContext":"System.Net.Http.HttpClient.ApiClient.ClientHandler","RequestId":"0HNMKDDQ9IJOR:00000001","RequestPath":"/join/joes-barbershop","ConnectionId":"0HNMKDDQ9IJOR","Scope":["HTTP GET http://localhost:5088/api/businesses/joes-barbershop"]}
{"@t":"2026-06-27T16:46:39.0139318Z","@mt":"Sending HTTP request {HttpMethod} {Uri}","@tr":"051da08c376a318135f414a621560b67","@sp":"6306551aaa02d548","HttpMethod":"GET","Uri":"http://localhost:5088/api/businesses/joes-barbershop","EventId":{"Id":100,"Name":"RequestStart"},"SourceContext":"System.Net.Http.HttpClient.ApiClient.ClientHandler","RequestId":"0HNMKDDQ9IJOO:00000002","RequestPath":"/join/joes-barbershop","ConnectionId":"0HNMKDDQ9IJOO","Scope":["HTTP GET http://localhost:5088/api/businesses/joes-barbershop"]}
{"@t":"2026-06-27T16:46:39.0155412Z","@mt":"Executed endpoint '{EndpointName}'","@tr":"e69d5aeff608af464d1135685912b5bd","@sp":"a7ebc95490a7ecc3","EndpointName":"Microsoft.AspNetCore.Routing.RouteEndpoint","EventId":{"Id":1,"Name":"ExecutedEndpoint"},"SourceContext":"Microsoft.AspNetCore.Routing.EndpointMiddleware","RequestId":"0HNMKDDQ9IJOM:00000004","RequestPath":"/_blazor/negotiate","ConnectionId":"0HNMKDDQ9IJOM"}
{"@t":"2026-06-27T16:46:39.0156893Z","@mt":"Request finished {Protocol} {Method} {Scheme}://{Host}{PathBase}{Path}{QueryString} - {StatusCode} {ContentLength} {ContentType} {ElapsedMilliseconds}ms","@tr":"e69d5aeff608af464d1135685912b5bd","@sp":"a7ebc95490a7ecc3","ElapsedMilliseconds":86647.1891,"StatusCode":200,"ContentType":"application/json","ContentLength":316,"Protocol":"HTTP/1.1","Method":"POST","Scheme":"http","Host":"localhost:5199","PathBase":"","Path":"/_blazor/negotiate","QueryString":"?negotiateVersion=1","EventId":{"Id":2},"SourceContext":"Microsoft.AspNetCore.Hosting.Diagnostics","RequestId":"0HNMKDDQ9IJOM:00000004","RequestPath":"/_blazor/negotiate","ConnectionId":"0HNMKDDQ9IJOM"}
{"@t":"2026-06-27T16:46:39.0258112Z","@mt":"Start processing HTTP request {HttpMethod} {Uri}","@tr":"ee659ee25ee2aad8b84be9fcd74ef6e0","@sp":"62d64e9dcfcf78d8","HttpMethod":"GET","Uri":"http://localhost:5088/api/businesses/joes-barbershop/queue","EventId":{"Id":100,"Name":"RequestPipelineStart"},"SourceContext":"System.Net.Http.HttpClient.ApiClient.LogicalHandler","RequestId":"0HNMKDDQ9IJOQ:00000001","RequestPath":"/staff/joes-barbershop","ConnectionId":"0HNMKDDQ9IJOQ","Scope":["HTTP GET http://localhost:5088/api/businesses/joes-barbershop/queue"]}
{"@t":"2026-06-27T16:46:39.0258112Z","@mt":"Start processing HTTP request {HttpMethod} {Uri}","@tr":"6d9c4cd39083b570bd53e1e73e59d5c2","@sp":"078e95f8234fa121","HttpMethod":"GET","Uri":"http://localhost:5088/api/businesses/joes-barbershop/queue","EventId":{"Id":100,"Name":"RequestPipelineStart"},"SourceContext":"System.Net.Http.HttpClient.ApiClient.LogicalHandler","RequestId":"0HNMKDDQ9IJOP:00000001","RequestPath":"/staff/joes-barbershop","ConnectionId":"0HNMKDDQ9IJOP","Scope":["HTTP GET http://localhost:5088/api/businesses/joes-barbershop/queue"]}
{"@t":"2026-06-27T16:46:39.0259277Z","@mt":"Sending HTTP request {HttpMethod} {Uri}","@tr":"ee659ee25ee2aad8b84be9fcd74ef6e0","@sp":"62d64e9dcfcf78d8","HttpMethod":"GET","Uri":"http://localhost:5088/api/businesses/joes-barbershop/queue","EventId":{"Id":100,"Name":"RequestStart"},"SourceContext":"System.Net.Http.HttpClient.ApiClient.ClientHandler","RequestId":"0HNMKDDQ9IJOQ:00000001","RequestPath":"/staff/joes-barbershop","ConnectionId":"0HNMKDDQ9IJOQ","Scope":["HTTP GET http://localhost:5088/api/businesses/joes-barbershop/queue"]}
{"@t":"2026-06-27T16:46:39.0259564Z","@mt":"Sending HTTP request {HttpMethod} {Uri}","@tr":"6d9c4cd39083b570bd53e1e73e59d5c2","@sp":"078e95f8234fa121","HttpMethod":"GET","Uri":"http://localhost:5088/api/businesses/joes-barbershop/queue","EventId":{"Id":100,"Name":"RequestStart"},"SourceContext":"System.Net.Http.HttpClient.ApiClient.ClientHandler","RequestId":"0HNMKDDQ9IJOP:00000001","RequestPath":"/staff/joes-barbershop","ConnectionId":"0HNMKDDQ9IJOP","Scope":["HTTP GET http://localhost:5088/api/businesses/joes-barbershop/queue"]}
{"@t":"2026-06-27T16:46:39.0686006Z","@mt":"Received HTTP response headers after {ElapsedMilliseconds}ms - {StatusCode}","@tr":"051da08c376a318135f414a621560b67","@sp":"6306551aaa02d548","ElapsedMilliseconds":54.6034,"StatusCode":200,"EventId":{"Id":101,"Name":"RequestEnd"},"SourceContext":"System.Net.Http.HttpClient.ApiClient.ClientHandler","HttpMethod":"GET","Uri":"http://localhost:5088/api/businesses/joes-barbershop","RequestId":"0HNMKDDQ9IJOO:00000002","RequestPath":"/join/joes-barbershop","ConnectionId":"0HNMKDDQ9IJOO","Scope":["HTTP GET http://localhost:5088/api/businesses/joes-barbershop"]}
{"@t":"2026-06-27T16:46:39.0687089Z","@mt":"Received HTTP response headers after {ElapsedMilliseconds}ms - {StatusCode}","@tr":"06ce8ac9184d06e0eae4eb29982e924a","@sp":"10a3dd9eb20f424d","ElapsedMilliseconds":54.7591,"StatusCode":200,"EventId":{"Id":101,"Name":"RequestEnd"},"SourceContext":"System.Net.Http.HttpClient.ApiClient.ClientHandler","HttpMethod":"GET","Uri":"http://localhost:5088/api/businesses/joes-barbershop","RequestId":"0HNMKDDQ9IJOR:00000001","RequestPath":"/join/joes-barbershop","ConnectionId":"0HNMKDDQ9IJOR","Scope":["HTTP GET http://localhost:5088/api/businesses/joes-barbershop"]}
{"@t":"2026-06-27T16:46:39.0687199Z","@mt":"End processing HTTP request after {ElapsedMilliseconds}ms - {StatusCode}","@tr":"051da08c376a318135f414a621560b67","@sp":"6306551aaa02d548","ElapsedMilliseconds":54.9568,"StatusCode":200,"EventId":{"Id":101,"Name":"RequestPipelineEnd"},"SourceContext":"System.Net.Http.HttpClient.ApiClient.LogicalHandler","HttpMethod":"GET","Uri":"http://localhost:5088/api/businesses/joes-barbershop","RequestId":"0HNMKDDQ9IJOO:00000002","RequestPath":"/join/joes-barbershop","ConnectionId":"0HNMKDDQ9IJOO","Scope":["HTTP GET http://localhost:5088/api/businesses/joes-barbershop"]}
{"@t":"2026-06-27T16:46:39.0687697Z","@mt":"End processing HTTP request after {ElapsedMilliseconds}ms - {StatusCode}","@tr":"06ce8ac9184d06e0eae4eb29982e924a","@sp":"10a3dd9eb20f424d","ElapsedMilliseconds":55.0082,"StatusCode":200,"EventId":{"Id":101,"Name":"RequestPipelineEnd"},"SourceContext":"System.Net.Http.HttpClient.ApiClient.LogicalHandler","HttpMethod":"GET","Uri":"http://localhost:5088/api/businesses/joes-barbershop","RequestId":"0HNMKDDQ9IJOR:00000001","RequestPath":"/join/joes-barbershop","ConnectionId":"0HNMKDDQ9IJOR","Scope":["HTTP GET http://localhost:5088/api/businesses/joes-barbershop"]}
{"@t":"2026-06-27T16:46:39.0700530Z","@mt":"Executed endpoint '{EndpointName}'","@tr":"051da08c376a318135f414a621560b67","@sp":"6306551aaa02d548","EndpointName":"/join/{Slug} (/join/{Slug})","EventId":{"Id":1,"Name":"ExecutedEndpoint"},"SourceContext":"Microsoft.AspNetCore.Routing.EndpointMiddleware","RequestId":"0HNMKDDQ9IJOO:00000002","RequestPath":"/join/joes-barbershop","ConnectionId":"0HNMKDDQ9IJOO"}
{"@t":"2026-06-27T16:46:39.0702744Z","@mt":"Request finished {Protocol} {Method} {Scheme}://{Host}{PathBase}{Path}{QueryString} - {StatusCode} {ContentLength} {ContentType} {ElapsedMilliseconds}ms","@tr":"051da08c376a318135f414a621560b67","@sp":"6306551aaa02d548","ElapsedMilliseconds":68745.0615,"StatusCode":200,"ContentType":"text/html; charset=utf-8","ContentLength":null,"Protocol":"HTTP/1.1","Method":"GET","Scheme":"http","Host":"localhost:5199","PathBase":"","Path":"/join/joes-barbershop","QueryString":"","EventId":{"Id":2},"SourceContext":"Microsoft.AspNetCore.Hosting.Diagnostics","RequestId":"0HNMKDDQ9IJOO:00000002","RequestPath":"/join/joes-barbershop","ConnectionId":"0HNMKDDQ9IJOO"}
{"@t":"2026-06-27T16:46:39.0713417Z","@mt":"Executed endpoint '{EndpointName}'","@tr":"06ce8ac9184d06e0eae4eb29982e924a","@sp":"10a3dd9eb20f424d","EndpointName":"/join/{Slug} (/join/{Slug})","EventId":{"Id":1,"Name":"ExecutedEndpoint"},"SourceContext":"Microsoft.AspNetCore.Routing.EndpointMiddleware","RequestId":"0HNMKDDQ9IJOR:00000001","RequestPath":"/join/joes-barbershop","ConnectionId":"0HNMKDDQ9IJOR"}
{"@t":"2026-06-27T16:46:39.0714365Z","@mt":"Request finished {Protocol} {Method} {Scheme}://{Host}{PathBase}{Path}{QueryString} - {StatusCode} {ContentLength} {ContentType} {ElapsedMilliseconds}ms","@tr":"06ce8ac9184d06e0eae4eb29982e924a","@sp":"10a3dd9eb20f424d","ElapsedMilliseconds":15572.4184,"StatusCode":200,"ContentType":"text/html; charset=utf-8","ContentLength":null,"Protocol":"HTTP/1.1","Method":"GET","Scheme":"http","Host":"localhost:5199","PathBase":"","Path":"/join/joes-barbershop","QueryString":"","EventId":{"Id":2},"SourceContext":"Microsoft.AspNetCore.Hosting.Diagnostics","RequestId":"0HNMKDDQ9IJOR:00000001","RequestPath":"/join/joes-barbershop","ConnectionId":"0HNMKDDQ9IJOR"}
{"@t":"2026-06-27T16:46:39.2509934Z","@mt":"Received HTTP response headers after {ElapsedMilliseconds}ms - {StatusCode}","@tr":"6d9c4cd39083b570bd53e1e73e59d5c2","@sp":"078e95f8234fa121","ElapsedMilliseconds":224.9808,"StatusCode":200,"EventId":{"Id":101,"Name":"RequestEnd"},"SourceContext":"System.Net.Http.HttpClient.ApiClient.ClientHandler","HttpMethod":"GET","Uri":"http://localhost:5088/api/businesses/joes-barbershop/queue","RequestId":"0HNMKDDQ9IJOP:00000001","RequestPath":"/staff/joes-barbershop","ConnectionId":"0HNMKDDQ9IJOP","Scope":["HTTP GET http://localhost:5088/api/businesses/joes-barbershop/queue"]}
{"@t":"2026-06-27T16:46:39.2509929Z","@mt":"Received HTTP response headers after {ElapsedMilliseconds}ms - {StatusCode}","@tr":"ee659ee25ee2aad8b84be9fcd74ef6e0","@sp":"62d64e9dcfcf78d8","ElapsedMilliseconds":225.0104,"StatusCode":200,"EventId":{"Id":101,"Name":"RequestEnd"},"SourceContext":"System.Net.Http.HttpClient.ApiClient.ClientHandler","HttpMethod":"GET","Uri":"http://localhost:5088/api/businesses/joes-barbershop/queue","RequestId":"0HNMKDDQ9IJOQ:00000001","RequestPath":"/staff/joes-barbershop","ConnectionId":"0HNMKDDQ9IJOQ","Scope":["HTTP GET http://localhost:5088/api/businesses/joes-barbershop/queue"]}
{"@t":"2026-06-27T16:46:39.2511116Z","@mt":"End processing HTTP request after {ElapsedMilliseconds}ms - {StatusCode}","@tr":"6d9c4cd39083b570bd53e1e73e59d5c2","@sp":"078e95f8234fa121","ElapsedMilliseconds":225.3246,"StatusCode":200,"EventId":{"Id":101,"Name":"RequestPipelineEnd"},"SourceContext":"System.Net.Http.HttpClient.ApiClient.LogicalHandler","HttpMethod":"GET","Uri":"http://localhost:5088/api/businesses/joes-barbershop/queue","RequestId":"0HNMKDDQ9IJOP:00000001","RequestPath":"/staff/joes-barbershop","ConnectionId":"0HNMKDDQ9IJOP","Scope":["HTTP GET http://localhost:5088/api/businesses/joes-barbershop/queue"]}
{"@t":"2026-06-27T16:46:39.2511620Z","@mt":"End processing HTTP request after {ElapsedMilliseconds}ms - {StatusCode}","@tr":"ee659ee25ee2aad8b84be9fcd74ef6e0","@sp":"62d64e9dcfcf78d8","ElapsedMilliseconds":225.3733,"StatusCode":200,"EventId":{"Id":101,"Name":"RequestPipelineEnd"},"SourceContext":"System.Net.Http.HttpClient.ApiClient.LogicalHandler","HttpMethod":"GET","Uri":"http://localhost:5088/api/businesses/joes-barbershop/queue","RequestId":"0HNMKDDQ9IJOQ:00000001","RequestPath":"/staff/joes-barbershop","ConnectionId":"0HNMKDDQ9IJOQ","Scope":["HTTP GET http://localhost:5088/api/businesses/joes-barbershop/queue"]}
{"@t":"2026-06-27T16:46:39.4308470Z","@mt":"SignalR connected.","@tr":"ee659ee25ee2aad8b84be9fcd74ef6e0","@sp":"62d64e9dcfcf78d8","SourceContext":"QueueIQ.Web.Services.QueueHubService","RequestId":"0HNMKDDQ9IJOQ:00000001","RequestPath":"/staff/joes-barbershop","ConnectionId":"0HNMKDDQ9IJOQ"}
{"@t":"2026-06-27T16:46:39.4308444Z","@mt":"SignalR connected.","@tr":"6d9c4cd39083b570bd53e1e73e59d5c2","@sp":"078e95f8234fa121","SourceContext":"QueueIQ.Web.Services.QueueHubService","RequestId":"0HNMKDDQ9IJOP:00000001","RequestPath":"/staff/joes-barbershop","ConnectionId":"0HNMKDDQ9IJOP"}
{"@t":"2026-06-27T16:46:39.4588277Z","@mt":"Joined queue group for {Slug}","@tr":"6d9c4cd39083b570bd53e1e73e59d5c2","@sp":"078e95f8234fa121","Slug":"joes-barbershop","SourceContext":"QueueIQ.Web.Services.QueueHubService","RequestId":"0HNMKDDQ9IJOP:00000001","RequestPath":"/staff/joes-barbershop","ConnectionId":"0HNMKDDQ9IJOP"}
{"@t":"2026-06-27T16:46:39.4588298Z","@mt":"Joined queue group for {Slug}","@tr":"ee659ee25ee2aad8b84be9fcd74ef6e0","@sp":"62d64e9dcfcf78d8","Slug":"joes-barbershop","SourceContext":"QueueIQ.Web.Services.QueueHubService","RequestId":"0HNMKDDQ9IJOQ:00000001","RequestPath":"/staff/joes-barbershop","ConnectionId":"0HNMKDDQ9IJOQ"}
{"@t":"2026-06-27T16:46:39.4595166Z","@mt":"Executed endpoint '{EndpointName}'","@tr":"6d9c4cd39083b570bd53e1e73e59d5c2","@sp":"078e95f8234fa121","EndpointName":"/staff/{Slug} (/staff/{Slug})","EventId":{"Id":1,"Name":"ExecutedEndpoint"},"SourceContext":"Microsoft.AspNetCore.Routing.EndpointMiddleware","RequestId":"0HNMKDDQ9IJOP:00000001","RequestPath":"/staff/joes-barbershop","ConnectionId":"0HNMKDDQ9IJOP"}
{"@t":"2026-06-27T16:46:39.4595167Z","@mt":"Executed endpoint '{EndpointName}'","@tr":"ee659ee25ee2aad8b84be9fcd74ef6e0","@sp":"62d64e9dcfcf78d8","EndpointName":"/staff/{Slug} (/staff/{Slug})","EventId":{"Id":1,"Name":"ExecutedEndpoint"},"SourceContext":"Microsoft.AspNetCore.Routing.EndpointMiddleware","RequestId":"0HNMKDDQ9IJOQ:00000001","RequestPath":"/staff/joes-barbershop","ConnectionId":"0HNMKDDQ9IJOQ"}
{"@t":"2026-06-27T16:46:39.4729379Z","@mt":"Request finished {Protocol} {Method} {Scheme}://{Host}{PathBase}{Path}{QueryString} - {StatusCode} {ContentLength} {ContentType} {ElapsedMilliseconds}ms","@tr":"ee659ee25ee2aad8b84be9fcd74ef6e0","@sp":"62d64e9dcfcf78d8","ElapsedMilliseconds":36498.8301,"StatusCode":200,"ContentType":"text/html; charset=utf-8","ContentLength":null,"Protocol":"HTTP/1.1","Method":"GET","Scheme":"http","Host":"localhost:5199","PathBase":"","Path":"/staff/joes-barbershop","QueryString":"","EventId":{"Id":2},"SourceContext":"Microsoft.AspNetCore.Hosting.Diagnostics","RequestId":"0HNMKDDQ9IJOQ:00000001","RequestPath":"/staff/joes-barbershop","ConnectionId":"0HNMKDDQ9IJOQ"}
{"@t":"2026-06-27T16:46:39.4729387Z","@mt":"Request finished {Protocol} {Method} {Scheme}://{Host}{PathBase}{Path}{QueryString} - {StatusCode} {ContentLength} {ContentType} {ElapsedMilliseconds}ms","@tr":"6d9c4cd39083b570bd53e1e73e59d5c2","@sp":"078e95f8234fa121","ElapsedMilliseconds":53961.774,"StatusCode":200,"ContentType":"text/html; charset=utf-8","ContentLength":null,"Protocol":"HTTP/1.1","Method":"GET","Scheme":"http","Host":"localhost:5199","PathBase":"","Path":"/staff/joes-barbershop","QueryString":"","EventId":{"Id":2},"SourceContext":"Microsoft.AspNetCore.Hosting.Diagnostics","RequestId":"0HNMKDDQ9IJOP:00000001","RequestPath":"/staff/joes-barbershop","ConnectionId":"0HNMKDDQ9IJOP"}
{"@t":"2026-06-27T16:48:01.4818569Z","@mt":"Request starting {Protocol} {Method} {Scheme}://{Host}{PathBase}{Path}{QueryString} - {ContentType} {ContentLength}","@tr":"d5cff52174b4b93a9aae85a12f7f717c","@sp":"d18d55d3ac802b1f","Protocol":"HTTP/1.1","Method":"GET","ContentType":null,"ContentLength":null,"Scheme":"http","Host":"localhost:5199","PathBase":"","Path":"/join/joes-barbershop","QueryString":"","EventId":{"Id":1},"SourceContext":"Microsoft.AspNetCore.Hosting.Diagnostics","RequestId":"0HNMKDDQ9IJOS:00000001","RequestPath":"/join/joes-barbershop","ConnectionId":"0HNMKDDQ9IJOS"}
{"@t":"2026-06-27T16:48:01.4822672Z","@mt":"Executing endpoint '{EndpointName}'","@tr":"d5cff52174b4b93a9aae85a12f7f717c","@sp":"d18d55d3ac802b1f","EndpointName":"/join/{Slug} (/join/{Slug})","EventId":{"Name":"ExecutingEndpoint"},"SourceContext":"Microsoft.AspNetCore.Routing.EndpointMiddleware","RequestId":"0HNMKDDQ9IJOS:00000001","RequestPath":"/join/joes-barbershop","ConnectionId":"0HNMKDDQ9IJOS"}
{"@t":"2026-06-27T16:48:01.4916449Z","@mt":"Start processing HTTP request {HttpMethod} {Uri}","@tr":"d5cff52174b4b93a9aae85a12f7f717c","@sp":"d18d55d3ac802b1f","HttpMethod":"GET","Uri":"http://localhost:5088/api/businesses/joes-barbershop","EventId":{"Id":100,"Name":"RequestPipelineStart"},"SourceContext":"System.Net.Http.HttpClient.ApiClient.LogicalHandler","RequestId":"0HNMKDDQ9IJOS:00000001","RequestPath":"/join/joes-barbershop","ConnectionId":"0HNMKDDQ9IJOS","Scope":["HTTP GET http://localhost:5088/api/businesses/joes-barbershop"]}
{"@t":"2026-06-27T16:48:01.4917452Z","@mt":"Sending HTTP request {HttpMethod} {Uri}","@tr":"d5cff52174b4b93a9aae85a12f7f717c","@sp":"d18d55d3ac802b1f","HttpMethod":"GET","Uri":"http://localhost:5088/api/businesses/joes-barbershop","EventId":{"Id":100,"Name":"RequestStart"},"SourceContext":"System.Net.Http.HttpClient.ApiClient.ClientHandler","RequestId":"0HNMKDDQ9IJOS:00000001","RequestPath":"/join/joes-barbershop","ConnectionId":"0HNMKDDQ9IJOS","Scope":["HTTP GET http://localhost:5088/api/businesses/joes-barbershop"]}
{"@t":"2026-06-27T16:48:01.4997451Z","@mt":"Received HTTP response headers after {ElapsedMilliseconds}ms - {StatusCode}","@tr":"d5cff52174b4b93a9aae85a12f7f717c","@sp":"d18d55d3ac802b1f","ElapsedMilliseconds":7.9368,"StatusCode":200,"EventId":{"Id":101,"Name":"RequestEnd"},"SourceContext":"System.Net.Http.HttpClient.ApiClient.ClientHandler","HttpMethod":"GET","Uri":"http://localhost:5088/api/businesses/joes-barbershop","RequestId":"0HNMKDDQ9IJOS:00000001","RequestPath":"/join/joes-barbershop","ConnectionId":"0HNMKDDQ9IJOS","Scope":["HTTP GET http://localhost:5088/api/businesses/joes-barbershop"]}
{"@t":"2026-06-27T16:48:01.4998678Z","@mt":"End processing HTTP request after {ElapsedMilliseconds}ms - {StatusCode}","@tr":"d5cff52174b4b93a9aae85a12f7f717c","@sp":"d18d55d3ac802b1f","ElapsedMilliseconds":8.2382,"StatusCode":200,"EventId":{"Id":101,"Name":"RequestPipelineEnd"},"SourceContext":"System.Net.Http.HttpClient.ApiClient.LogicalHandler","HttpMethod":"GET","Uri":"http://localhost:5088/api/businesses/joes-barbershop","RequestId":"0HNMKDDQ9IJOS:00000001","RequestPath":"/join/joes-barbershop","ConnectionId":"0HNMKDDQ9IJOS","Scope":["HTTP GET http://localhost:5088/api/businesses/joes-barbershop"]}
{"@t":"2026-06-27T16:48:01.5010883Z","@mt":"Executed endpoint '{EndpointName}'","@tr":"d5cff52174b4b93a9aae85a12f7f717c","@sp":"d18d55d3ac802b1f","EndpointName":"/join/{Slug} (/join/{Slug})","EventId":{"Id":1,"Name":"ExecutedEndpoint"},"SourceContext":"Microsoft.AspNetCore.Routing.EndpointMiddleware","RequestId":"0HNMKDDQ9IJOS:00000001","RequestPath":"/join/joes-barbershop","ConnectionId":"0HNMKDDQ9IJOS"}
{"@t":"2026-06-27T16:48:01.5012980Z","@mt":"Request finished {Protocol} {Method} {Scheme}://{Host}{PathBase}{Path}{QueryString} - {StatusCode} {ContentLength} {ContentType} {ElapsedMilliseconds}ms","@tr":"d5cff52174b4b93a9aae85a12f7f717c","@sp":"d18d55d3ac802b1f","ElapsedMilliseconds":19.431,"StatusCode":200,"ContentType":"text/html; charset=utf-8","ContentLength":null,"Protocol":"HTTP/1.1","Method":"GET","Scheme":"http","Host":"localhost:5199","PathBase":"","Path":"/join/joes-barbershop","QueryString":"","EventId":{"Id":2},"SourceContext":"Microsoft.AspNetCore.Hosting.Diagnostics","RequestId":"0HNMKDDQ9IJOS:00000001","RequestPath":"/join/joes-barbershop","ConnectionId":"0HNMKDDQ9IJOS"}
{"@t":"2026-06-27T16:48:01.5212800Z","@mt":"Request starting {Protocol} {Method} {Scheme}://{Host}{PathBase}{Path}{QueryString} - {ContentType} {ContentLength}","@tr":"7bbc8d0e0c62cd935dd7ac63e9560083","@sp":"6de2eee29e20a546","Protocol":"HTTP/1.1","Method":"GET","ContentType":null,"ContentLength":null,"Scheme":"http","Host":"localhost:5199","PathBase":"","Path":"/app.9msw5ztgru.css","QueryString":"","EventId":{"Id":1},"SourceContext":"Microsoft.AspNetCore.Hosting.Diagnostics","RequestId":"0HNMKDDQ9IJOS:00000002","RequestPath":"/app.9msw5ztgru.css","ConnectionId":"0HNMKDDQ9IJOS"}
{"@t":"2026-06-27T16:48:01.5217239Z","@mt":"Executing endpoint '{EndpointName}'","@tr":"7bbc8d0e0c62cd935dd7ac63e9560083","@sp":"6de2eee29e20a546","EndpointName":"Microsoft.AspNetCore.Routing.RouteEndpoint","EventId":{"Name":"ExecutingEndpoint"},"SourceContext":"Microsoft.AspNetCore.Routing.EndpointMiddleware","RequestId":"0HNMKDDQ9IJOS:00000002","RequestPath":"/app.9msw5ztgru.css","ConnectionId":"0HNMKDDQ9IJOS"}
{"@t":"2026-06-27T16:48:01.5221627Z","@mt":"Request starting {Protocol} {Method} {Scheme}://{Host}{PathBase}{Path}{QueryString} - {ContentType} {ContentLength}","@tr":"21d66a1c977c0f0e6cb02a8d98246cf9","@sp":"a471b53aef039e71","Protocol":"HTTP/1.1","Method":"GET","ContentType":null,"ContentLength":null,"Scheme":"http","Host":"localhost:5199","PathBase":"","Path":"/QueueIQ.Web.dvyq0oszyw.styles.css","QueryString":"","EventId":{"Id":1},"SourceContext":"Microsoft.AspNetCore.Hosting.Diagnostics","RequestId":"0HNMKDDQ9IJOT:00000001","RequestPath":"/QueueIQ.Web.dvyq0oszyw.styles.css","ConnectionId":"0HNMKDDQ9IJOT"}
{"@t":"2026-06-27T16:48:01.5223996Z","@mt":"Executing endpoint '{EndpointName}'","@tr":"21d66a1c977c0f0e6cb02a8d98246cf9","@sp":"a471b53aef039e71","EndpointName":"Microsoft.AspNetCore.Routing.RouteEndpoint","EventId":{"Name":"ExecutingEndpoint"},"SourceContext":"Microsoft.AspNetCore.Routing.EndpointMiddleware","RequestId":"0HNMKDDQ9IJOT:00000001","RequestPath":"/QueueIQ.Web.dvyq0oszyw.styles.css","ConnectionId":"0HNMKDDQ9IJOT"}
{"@t":"2026-06-27T16:48:01.5227031Z","@mt":"Request starting {Protocol} {Method} {Scheme}://{Host}{PathBase}{Path}{QueryString} - {ContentType} {ContentLength}","@tr":"884070a6480142a39e2a108477f3b5b2","@sp":"6d332c8611a3dd7f","Protocol":"HTTP/1.1","Method":"GET","ContentType":null,"ContentLength":null,"Scheme":"http","Host":"localhost:5199","PathBase":"","Path":"/_framework/blazor.web.js","QueryString":"","EventId":{"Id":1},"SourceContext":"Microsoft.AspNetCore.Hosting.Diagnostics","RequestId":"0HNMKDDQ9IJOU:00000001","RequestPath":"/_framework/blazor.web.js","ConnectionId":"0HNMKDDQ9IJOU"}
{"@t":"2026-06-27T16:48:01.5232951Z","@mt":"Sending file. Request path: '{VirtualPath}'. Physical path: '{PhysicalPath}'","@tr":"21d66a1c977c0f0e6cb02a8d98246cf9","@sp":"a471b53aef039e71","VirtualPath":"QueueIQ.Web.dvyq0oszyw.styles.css","PhysicalPath":"C:\\Users\\Joseph\\Documents\\QueueIQ\\src\\QueueIQ.Web\\obj\\Debug\\net9.0\\compressed\\le3gd6ksss-dvyq0oszyw.gz","EventId":{"Id":2,"Name":"FileServed"},"SourceContext":"Microsoft.AspNetCore.StaticAssets.StaticAssetsInvoker","RequestId":"0HNMKDDQ9IJOT:00000001","RequestPath":"/QueueIQ.Web.dvyq0oszyw.styles.css","ConnectionId":"0HNMKDDQ9IJOT"}
{"@t":"2026-06-27T16:48:01.5233577Z","@mt":"Sending file. Request path: '{VirtualPath}'. Physical path: '{PhysicalPath}'","@tr":"7bbc8d0e0c62cd935dd7ac63e9560083","@sp":"6de2eee29e20a546","VirtualPath":"app.9msw5ztgru.css","PhysicalPath":"C:\\Users\\Joseph\\Documents\\QueueIQ\\src\\QueueIQ.Web\\obj\\Debug\\net9.0\\compressed\\jxu4ldg72n-9msw5ztgru.gz","EventId":{"Id":2,"Name":"FileServed"},"SourceContext":"Microsoft.AspNetCore.StaticAssets.StaticAssetsInvoker","RequestId":"0HNMKDDQ9IJOS:00000002","RequestPath":"/app.9msw5ztgru.css","ConnectionId":"0HNMKDDQ9IJOS"}
{"@t":"2026-06-27T16:48:01.5233550Z","@mt":"Executed endpoint '{EndpointName}'","@tr":"21d66a1c977c0f0e6cb02a8d98246cf9","@sp":"a471b53aef039e71","EndpointName":"Microsoft.AspNetCore.Routing.RouteEndpoint","EventId":{"Id":1,"Name":"ExecutedEndpoint"},"SourceContext":"Microsoft.AspNetCore.Routing.EndpointMiddleware","RequestId":"0HNMKDDQ9IJOT:00000001","RequestPath":"/QueueIQ.Web.dvyq0oszyw.styles.css","ConnectionId":"0HNMKDDQ9IJOT"}
{"@t":"2026-06-27T16:48:01.5234056Z","@mt":"Executed endpoint '{EndpointName}'","@tr":"7bbc8d0e0c62cd935dd7ac63e9560083","@sp":"6de2eee29e20a546","EndpointName":"Microsoft.AspNetCore.Routing.RouteEndpoint","EventId":{"Id":1,"Name":"ExecutedEndpoint"},"SourceContext":"Microsoft.AspNetCore.Routing.EndpointMiddleware","RequestId":"0HNMKDDQ9IJOS:00000002","RequestPath":"/app.9msw5ztgru.css","ConnectionId":"0HNMKDDQ9IJOS"}
{"@t":"2026-06-27T16:48:01.5234906Z","@mt":"Request finished {Protocol} {Method} {Scheme}://{Host}{PathBase}{Path}{QueryString} - {StatusCode} {ContentLength} {ContentType} {ElapsedMilliseconds}ms","@tr":"21d66a1c977c0f0e6cb02a8d98246cf9","@sp":"a471b53aef039e71","ElapsedMilliseconds":1.3129,"StatusCode":200,"ContentType":"text/css","ContentLength":595,"Protocol":"HTTP/1.1","Method":"GET","Scheme":"http","Host":"localhost:5199","PathBase":"","Path":"/QueueIQ.Web.dvyq0oszyw.styles.css","QueryString":"","EventId":{"Id":2},"SourceContext":"Microsoft.AspNetCore.Hosting.Diagnostics","RequestId":"0HNMKDDQ9IJOT:00000001","RequestPath":"/QueueIQ.Web.dvyq0oszyw.styles.css","ConnectionId":"0HNMKDDQ9IJOT"}
{"@t":"2026-06-27T16:48:01.5235035Z","@mt":"Request finished {Protocol} {Method} {Scheme}://{Host}{PathBase}{Path}{QueryString} - {StatusCode} {ContentLength} {ContentType} {ElapsedMilliseconds}ms","@tr":"7bbc8d0e0c62cd935dd7ac63e9560083","@sp":"6de2eee29e20a546","ElapsedMilliseconds":2.2229,"StatusCode":200,"ContentType":"text/css","ContentLength":5705,"Protocol":"HTTP/1.1","Method":"GET","Scheme":"http","Host":"localhost:5199","PathBase":"","Path":"/app.9msw5ztgru.css","QueryString":"","EventId":{"Id":2},"SourceContext":"Microsoft.AspNetCore.Hosting.Diagnostics","RequestId":"0HNMKDDQ9IJOS:00000002","RequestPath":"/app.9msw5ztgru.css","ConnectionId":"0HNMKDDQ9IJOS"}
{"@t":"2026-06-27T16:48:01.5238961Z","@mt":"Executing endpoint '{EndpointName}'","@tr":"884070a6480142a39e2a108477f3b5b2","@sp":"6d332c8611a3dd7f","EndpointName":"Blazor web static files","EventId":{"Name":"ExecutingEndpoint"},"SourceContext":"Microsoft.AspNetCore.Routing.EndpointMiddleware","RequestId":"0HNMKDDQ9IJOU:00000001","RequestPath":"/_framework/blazor.web.js","ConnectionId":"0HNMKDDQ9IJOU"}
{"@t":"2026-06-27T16:48:01.5241124Z","@mt":"The file {Path} was not modified","@tr":"884070a6480142a39e2a108477f3b5b2","@sp":"6d332c8611a3dd7f","Path":"/_framework/blazor.web.js","EventId":{"Id":6,"Name":"FileNotModified"},"SourceContext":"Microsoft.AspNetCore.StaticFiles.StaticFileMiddleware","RequestId":"0HNMKDDQ9IJOU:00000001","RequestPath":"/_framework/blazor.web.js","ConnectionId":"0HNMKDDQ9IJOU"}
{"@t":"2026-06-27T16:48:01.5241815Z","@mt":"Executed endpoint '{EndpointName}'","@tr":"884070a6480142a39e2a108477f3b5b2","@sp":"6d332c8611a3dd7f","EndpointName":"Blazor web static files","EventId":{"Id":1,"Name":"ExecutedEndpoint"},"SourceContext":"Microsoft.AspNetCore.Routing.EndpointMiddleware","RequestId":"0HNMKDDQ9IJOU:00000001","RequestPath":"/_framework/blazor.web.js","ConnectionId":"0HNMKDDQ9IJOU"}
{"@t":"2026-06-27T16:48:01.5242421Z","@mt":"Request finished {Protocol} {Method} {Scheme}://{Host}{PathBase}{Path}{QueryString} - {StatusCode} {ContentLength} {ContentType} {ElapsedMilliseconds}ms","@tr":"884070a6480142a39e2a108477f3b5b2","@sp":"6d332c8611a3dd7f","ElapsedMilliseconds":1.5355,"StatusCode":304,"ContentType":"text/javascript","ContentLength":null,"Protocol":"HTTP/1.1","Method":"GET","Scheme":"http","Host":"localhost:5199","PathBase":"","Path":"/_framework/blazor.web.js","QueryString":"","EventId":{"Id":2},"SourceContext":"Microsoft.AspNetCore.Hosting.Diagnostics","RequestId":"0HNMKDDQ9IJOU:00000001","RequestPath":"/_framework/blazor.web.js","ConnectionId":"0HNMKDDQ9IJOU"}
{"@t":"2026-06-27T16:48:01.5777104Z","@mt":"Request starting {Protocol} {Method} {Scheme}://{Host}{PathBase}{Path}{QueryString} - {ContentType} {ContentLength}","@tr":"c1a9f5327ec83b55449750e4022635d4","@sp":"1a496251dbfb8210","Protocol":"HTTP/1.1","Method":"GET","ContentType":null,"ContentLength":null,"Scheme":"http","Host":"localhost:5199","PathBase":"","Path":"/_blazor/initializers","QueryString":"","EventId":{"Id":1},"SourceContext":"Microsoft.AspNetCore.Hosting.Diagnostics","RequestId":"0HNMKDDQ9IJOT:00000002","RequestPath":"/_blazor/initializers","ConnectionId":"0HNMKDDQ9IJOT"}
{"@t":"2026-06-27T16:48:01.5782011Z","@mt":"Executing endpoint '{EndpointName}'","@tr":"c1a9f5327ec83b55449750e4022635d4","@sp":"1a496251dbfb8210","EndpointName":"Microsoft.AspNetCore.Routing.RouteEndpoint","EventId":{"Name":"ExecutingEndpoint"},"SourceContext":"Microsoft.AspNetCore.Routing.EndpointMiddleware","RequestId":"0HNMKDDQ9IJOT:00000002","RequestPath":"/_blazor/initializers","ConnectionId":"0HNMKDDQ9IJOT"}
{"@t":"2026-06-27T16:48:01.5787343Z","@mt":"Executed endpoint '{EndpointName}'","@tr":"c1a9f5327ec83b55449750e4022635d4","@sp":"1a496251dbfb8210","EndpointName":"Microsoft.AspNetCore.Routing.RouteEndpoint","EventId":{"Id":1,"Name":"ExecutedEndpoint"},"SourceContext":"Microsoft.AspNetCore.Routing.EndpointMiddleware","RequestId":"0HNMKDDQ9IJOT:00000002","RequestPath":"/_blazor/initializers","ConnectionId":"0HNMKDDQ9IJOT"}
{"@t":"2026-06-27T16:48:01.5788633Z","@mt":"Request finished {Protocol} {Method} {Scheme}://{Host}{PathBase}{Path}{QueryString} - {StatusCode} {ContentLength} {ContentType} {ElapsedMilliseconds}ms","@tr":"c1a9f5327ec83b55449750e4022635d4","@sp":"1a496251dbfb8210","ElapsedMilliseconds":1.1472,"StatusCode":200,"ContentType":"application/json; charset=utf-8","ContentLength":null,"Protocol":"HTTP/1.1","Method":"GET","Scheme":"http","Host":"localhost:5199","PathBase":"","Path":"/_blazor/initializers","QueryString":"","EventId":{"Id":2},"SourceContext":"Microsoft.AspNetCore.Hosting.Diagnostics","RequestId":"0HNMKDDQ9IJOT:00000002","RequestPath":"/_blazor/initializers","ConnectionId":"0HNMKDDQ9IJOT"}
{"@t":"2026-06-27T16:48:01.5905985Z","@mt":"Request starting {Protocol} {Method} {Scheme}://{Host}{PathBase}{Path}{QueryString} - {ContentType} {ContentLength}","@tr":"f226f113852f305fd1a95f764792e33d","@sp":"bbc600513206f301","Protocol":"HTTP/1.1","Method":"POST","ContentType":null,"ContentLength":0,"Scheme":"http","Host":"localhost:5199","PathBase":"","Path":"/_blazor/negotiate","QueryString":"?negotiateVersion=1","EventId":{"Id":1},"SourceContext":"Microsoft.AspNetCore.Hosting.Diagnostics","RequestId":"0HNMKDDQ9IJOT:00000003","RequestPath":"/_blazor/negotiate","ConnectionId":"0HNMKDDQ9IJOT"}
{"@t":"2026-06-27T16:48:01.5907550Z","@mt":"Executing endpoint '{EndpointName}'","@tr":"f226f113852f305fd1a95f764792e33d","@sp":"bbc600513206f301","EndpointName":"Microsoft.AspNetCore.Routing.RouteEndpoint","EventId":{"Name":"ExecutingEndpoint"},"SourceContext":"Microsoft.AspNetCore.Routing.EndpointMiddleware","RequestId":"0HNMKDDQ9IJOT:00000003","RequestPath":"/_blazor/negotiate","ConnectionId":"0HNMKDDQ9IJOT"}
{"@t":"2026-06-27T16:48:01.5910883Z","@mt":"Executed endpoint '{EndpointName}'","@tr":"f226f113852f305fd1a95f764792e33d","@sp":"bbc600513206f301","EndpointName":"Microsoft.AspNetCore.Routing.RouteEndpoint","EventId":{"Id":1,"Name":"ExecutedEndpoint"},"SourceContext":"Microsoft.AspNetCore.Routing.EndpointMiddleware","RequestId":"0HNMKDDQ9IJOT:00000003","RequestPath":"/_blazor/negotiate","ConnectionId":"0HNMKDDQ9IJOT"}
{"@t":"2026-06-27T16:48:01.5911589Z","@mt":"Request finished {Protocol} {Method} {Scheme}://{Host}{PathBase}{Path}{QueryString} - {StatusCode} {ContentLength} {ContentType} {ElapsedMilliseconds}ms","@tr":"f226f113852f305fd1a95f764792e33d","@sp":"bbc600513206f301","ElapsedMilliseconds":0.5631,"StatusCode":200,"ContentType":"application/json","ContentLength":316,"Protocol":"HTTP/1.1","Method":"POST","Scheme":"http","Host":"localhost:5199","PathBase":"","Path":"/_blazor/negotiate","QueryString":"?negotiateVersion=1","EventId":{"Id":2},"SourceContext":"Microsoft.AspNetCore.Hosting.Diagnostics","RequestId":"0HNMKDDQ9IJOT:00000003","RequestPath":"/_blazor/negotiate","ConnectionId":"0HNMKDDQ9IJOT"}
{"@t":"2026-06-27T16:48:01.5957788Z","@mt":"Request starting {Protocol} {Method} {Scheme}://{Host}{PathBase}{Path}{QueryString} - {ContentType} {ContentLength}","@tr":"ccfdab8423f0ea5345a513e83fa5745f","@sp":"89b4e658ac90ac02","Protocol":"HTTP/1.1","Method":"GET","ContentType":null,"ContentLength":null,"Scheme":"http","Host":"localhost:5199","PathBase":"","Path":"/_blazor","QueryString":"?id=7cw7c1FeWNcCZf6DZBF1QQ","EventId":{"Id":1},"SourceContext":"Microsoft.AspNetCore.Hosting.Diagnostics","RequestId":"0HNMKDDQ9IJOV:00000001","RequestPath":"/_blazor","ConnectionId":"0HNMKDDQ9IJOV"}
{"@t":"2026-06-27T16:48:01.5960864Z","@mt":"Executing endpoint '{EndpointName}'","@tr":"ccfdab8423f0ea5345a513e83fa5745f","@sp":"89b4e658ac90ac02","EndpointName":"Microsoft.AspNetCore.Routing.RouteEndpoint","EventId":{"Name":"ExecutingEndpoint"},"SourceContext":"Microsoft.AspNetCore.Routing.EndpointMiddleware","RequestId":"0HNMKDDQ9IJOV:00000001","RequestPath":"/_blazor","ConnectionId":"0HNMKDDQ9IJOV"}
{"@t":"2026-06-27T16:48:01.6135755Z","@mt":"Request starting {Protocol} {Method} {Scheme}://{Host}{PathBase}{Path}{QueryString} - {ContentType} {ContentLength}","@tr":"be95126cfe5b3b78911eb747225408e4","@sp":"c1e427ae5824dcdb","Protocol":"HTTP/1.1","Method":"GET","ContentType":null,"ContentLength":null,"Scheme":"http","Host":"localhost:5199","PathBase":"","Path":"/favicon.ico","QueryString":"","EventId":{"Id":1},"SourceContext":"Microsoft.AspNetCore.Hosting.Diagnostics","RequestId":"0HNMKDDQ9IJOT:00000004","RequestPath":"/favicon.ico","ConnectionId":"0HNMKDDQ9IJOT"}
{"@t":"2026-06-27T16:48:01.6139008Z","@mt":"Request finished {Protocol} {Method} {Scheme}://{Host}{PathBase}{Path}{QueryString} - {StatusCode} {ContentLength} {ContentType} {ElapsedMilliseconds}ms","@tr":"be95126cfe5b3b78911eb747225408e4","@sp":"c1e427ae5824dcdb","ElapsedMilliseconds":0.3265,"StatusCode":404,"ContentType":null,"ContentLength":0,"Protocol":"HTTP/1.1","Method":"GET","Scheme":"http","Host":"localhost:5199","PathBase":"","Path":"/favicon.ico","QueryString":"","EventId":{"Id":2},"SourceContext":"Microsoft.AspNetCore.Hosting.Diagnostics","RequestId":"0HNMKDDQ9IJOT:00000004","RequestPath":"/favicon.ico","ConnectionId":"0HNMKDDQ9IJOT"}
{"@t":"2026-06-27T16:48:01.6140277Z","@mt":"Request reached the end of the middleware pipeline without being handled by application code. Request path: {Method} {Scheme}://{Host}{PathBase}{Path}, Response status code: {StatusCode}","@tr":"be95126cfe5b3b78911eb747225408e4","@sp":"c1e427ae5824dcdb","Method":"GET","Scheme":"http","Host":"localhost:5199","PathBase":"","Path":"/favicon.ico","StatusCode":404,"EventId":{"Id":16},"SourceContext":"Microsoft.AspNetCore.Hosting.Diagnostics","RequestId":"0HNMKDDQ9IJOT:00000004","RequestPath":"/favicon.ico","ConnectionId":"0HNMKDDQ9IJOT"}
{"@t":"2026-06-27T16:48:01.6369756Z","@mt":"Executed endpoint '{EndpointName}'","@tr":"ccfdab8423f0ea5345a513e83fa5745f","@sp":"89b4e658ac90ac02","EndpointName":"Microsoft.AspNetCore.Routing.RouteEndpoint","EventId":{"Id":1,"Name":"ExecutedEndpoint"},"SourceContext":"Microsoft.AspNetCore.Routing.EndpointMiddleware","RequestId":"0HNMKDDQ9IJOV:00000001","RequestPath":"/_blazor","ConnectionId":"0HNMKDDQ9IJOV"}
{"@t":"2026-06-27T16:48:01.6371007Z","@mt":"Request finished {Protocol} {Method} {Scheme}://{Host}{PathBase}{Path}{QueryString} - {StatusCode} {ContentLength} {ContentType} {ElapsedMilliseconds}ms","@tr":"ccfdab8423f0ea5345a513e83fa5745f","@sp":"89b4e658ac90ac02","ElapsedMilliseconds":41.305,"StatusCode":101,"ContentType":null,"ContentLength":null,"Protocol":"HTTP/1.1","Method":"GET","Scheme":"http","Host":"localhost:5199","PathBase":"","Path":"/_blazor","QueryString":"?id=7cw7c1FeWNcCZf6DZBF1QQ","EventId":{"Id":2},"SourceContext":"Microsoft.AspNetCore.Hosting.Diagnostics","RequestId":"0HNMKDDQ9IJOV:00000001","RequestPath":"/_blazor","ConnectionId":"0HNMKDDQ9IJOV"}
